{"inkVersion":20,"root":[[{"#":"theme: dark"},{"#":"author: Avery Hiebert"},"\n","\n","\n","\n","\n","\n","\n","\n","\n","\n","ev",false,"/ev",[{"->":".^.b","c":true},{"b":["\n","ev",{"VAR?":"debug_location"},"/ev",{"VAR=":"current_location","re":true},"ev",{"VAR?":"p4"},{"f()":"kill"},"pop","/ev","\n",{"->":"0.16"},null]}],"nop","\n",{"->":"start"},["done",{"#n":"g-0"}],null],"done",{"start":[["^A remote arctic town is facing an impending diptheria outbreak.","\n","^All of the town's antitoxin serum is expired.","\n","^The only way to get the serum to them in time is by dogsled.","\n","^The journey will be perilous. Godspeed, brave travellers.","\n","ev","str","^Start your journey...","/str","/ev",{"*":".^.c-0","flg":4},{"c-0":["\n","ev",2,"/ev",{"->":"select_starting_inventory"},null]}],null],"select_starting_inventory":[{"temp=":"selections_remaining"},["ev",{"VAR?":"selections_remaining"},0,"==","/ev",[{"->":".^.b","c":true},{"b":["\n",{"->":"choose_next_destination"},{"->":".^.^.^.6"},null]}],"nop","\n",{"#":"CLEAR"},"^Select ","ev",{"VAR?":"selections_remaining"},"out","/ev","^ ",["ev","visit",1,"MIN","/ev","ev","du",0,"==","/ev",{"->":".^.s0","c":true},"ev","du",1,"==","/ev",{"->":".^.s1","c":true},"nop",{"s0":["pop",{"->":".^.^.17"},null],"s1":["pop","^more",{"->":".^.^.17"},null],"#f":5}],"^ ","ev",{"VAR?":"selections_remaining"},1,">","/ev",[{"->":".^.b","c":true},{"b":["^items",{"->":".^.^.^.24"},null]}],[{"->":".^.b"},{"b":["^item",{"->":".^.^.^.24"},null]}],"nop","^ before you set out:","\n","ev","str","^Shotgun","/str",{"VAR?":"inventory"},{"VAR?":"shotgun"},"?","!","/ev",{"*":".^.c-0","flg":21},"ev","str","^Bedroll","/str",{"VAR?":"inventory"},{"VAR?":"bedroll"},"?","!","/ev",{"*":".^.c-1","flg":21},"ev","str","^Harmonica","/str",{"VAR?":"inventory"},{"VAR?":"harmonica"},"?","!","/ev",{"*":".^.c-2","flg":21},"ev","str","^Kerosene Lamp","/str",{"VAR?":"inventory"},{"VAR?":"lamp"},"?","!","/ev",{"*":".^.c-3","flg":21},"ev","str","^Saucepan","/str",{"VAR?":"inventory"},{"VAR?":"saucepan"},"?","!","/ev",{"*":".^.c-4","flg":21},{"c-0":["\n","ev",{"VAR?":"inventory"},{"VAR?":"shotgun"},"+",{"VAR=":"inventory","re":true},"/ev",{"->":".^.^.g-0"},{"#f":5}],"c-1":["\n","ev",{"VAR?":"inventory"},{"VAR?":"bedroll"},"+",{"VAR=":"inventory","re":true},"/ev",{"->":".^.^.g-0"},{"#f":5}],"c-2":["\n","ev",{"VAR?":"inventory"},{"VAR?":"harmonica"},"+",{"VAR=":"inventory","re":true},"/ev",{"->":".^.^.g-0"},{"#f":5}],"c-3":["\n","ev",{"VAR?":"inventory"},{"VAR?":"lamp"},"+",{"VAR=":"inventory","re":true},"/ev",{"->":".^.^.g-0"},{"#f":5}],"c-4":["\n","ev",{"VAR?":"inventory"},{"VAR?":"saucepan"},"+",{"VAR=":"inventory","re":true},"/ev",{"->":".^.^.g-0"},{"#f":5}],"g-0":["ev",{"VAR?":"selections_remaining"},1,"-","/ev",{"->":".^.^.^"},null]}],null],"standard_menu_options":[{"temp=":"back"},["ev","str","^((Check party status))","/str",true,"/ev",{"*":".^.c-0","flg":5},{"c-0":["\n",{"#":"CLEAR"},"^Inventory: ","ev",{"VAR?":"inventory"},"out","/ev","\n","ev",{"VAR?":"party"},{"^->":"summarize_status"},{"f()":"for_each"},"pop","/ev","\n",["ev","str","^Done.","/str","/ev",{"*":".^.c-0","flg":4},{"c-0":["\n",{"#":"CLEAR"},{"->":"back","var":true},null]}],null]}],null],"check_loss":[["ev",{"VAR?":"hours_remaining"},1,"<","/ev",{"->":".^.b","c":true},{"b":["\n","ev",false,"/ev",{"VAR=":"currently_moving","re":true},{"->":"endings.out_of_time"},{"->":".^.^.^.2"},null]}],["ev",{"VAR?":"party"},"LIST_COUNT",0,"==","/ev",{"->":".^.b","c":true},{"b":["\n","ev",false,"/ev",{"VAR=":"currently_moving","re":true},{"->":"endings.all_dead"},{"->":".^.^.^.2"},null]}],"nop","\n","ev","void","/ev","->->",null],"endings":[{"->":".^.out_of_time"},{"out_of_time":["^Unfortunately, you did not get to the town fast enough to avert the epidemic.","\n","ev",{"VAR?":"dead"},"LIST_COUNT",0,">","/ev",[{"->":".^.b","c":true},{"b":["\n","ev",{"VAR?":"dead"},"str","^","/str",{"f()":"listNamesWithCommas"},"out","/ev","^ died in vain.","\n",{"->":".^.^.^.9"},null]}],"nop","\n","^(BAD ENDING) ",{"#":"bad"},"\n","end",null],"all_dead":["^Your entire party is dead. The serum is lost.  Thousands will perish.","\n","^(BAD ENDING) ",{"#":"bad"},"\n","end",null],"win":["ev",false,"/ev",{"VAR=":"currently_moving","re":true},"^At last, you arrive at your destination with the serum safely intact.","\n","^The epidemic is averted!","\n","ev",{"VAR?":"dead"},"LIST_COUNT",0,">","/ev",[{"->":".^.b","c":true},{"b":["\n","ev",{"VAR?":"dead"},"str","^","/str",{"f()":"listNamesWithCommas"},"out","/ev","^ may have perished, but they will be remembered as ","ev",{"VAR?":"dead"},"LIST_COUNT",1,">","/ev",[{"->":".^.b","c":true},{"b":["^heroes",{"->":".^.^.^.18"},null]}],[{"->":".^.b"},{"b":["^a hero",{"->":".^.^.^.18"},null]}],"nop","^.","\n",{"->":".^.^.^.15"},null]}],"nop","\n","^(GOOD ENDING) ",{"#":"good"},"\n","end",null]}],"for_each":[{"temp=":"func"},{"temp=":"ls"},"ev",{"VAR?":"ls"},"LIST_COUNT",0,"==","/ev",[{"->":".^.b","c":true},{"b":["\n","ev","void","/ev","~ret",{"->":".^.^.^.9"},null]}],"nop","\n","ev",{"VAR?":"ls"},"LIST_MIN","/ev",{"temp=":"item"},"\n","ev",{"VAR?":"item"},{"f()":"func","var":true},"out","/ev","\n","ev",{"VAR?":"ls"},{"VAR?":"item"},"-",{"VAR?":"func"},{"f()":".^"},"/ev","~ret","\n",null],"note":[{"temp=":"type"},{"temp=":"msg"},"ev",true,"!","/ev",[{"->":".^.b","c":true},{"b":["\n","ev","void","/ev","~ret",{"->":"note.7"},null]}],"nop","\n","ev",{"VAR?":"type"},{"VAR?":"good"},"==","/ev",[{"->":".^.b","c":true},{"b":["\n",{"#":"good"},{"->":"note.16"},null]}],[{"->":".^.b"},{"b":["\n",{"#":"bad"},{"->":"note.16"},null]}],"nop","\n","ev",{"VAR?":"msg"},"out","/ev","\n",null],"confirm":[["ev","str","^Ok","/str","/ev",{"*":".^.c-0","flg":4},{"c-0":["\n","ev","void","/ev","->->",null]}],null],"select_from":[{"temp=":"people"},"ev",{"VAR?":"people"},"LIST_COUNT",0,"==","/ev",[{"->":".^.b","c":true},{"b":["\n","ev",false,"/ev","~ret",{"->":".^.^.^.9"},null]}],[{"->":".^.b"},{"b":["\n","ev",{"VAR?":"people"},"lrnd","/ev",{"VAR=":"WHO","re":true},"\n","ev",true,"/ev","~ret",{"->":".^.^.^.9"},null]}],"nop","\n",null],"listNamesWithCommas":[{"temp=":"if_empty"},{"temp=":"list"},"ev",{"VAR?":"list"},"LIST_COUNT","/ev",["du","ev",2,"==","/ev",{"->":".^.b","c":true},{"b":["pop","\n","ev",{"VAR?":"list"},"LIST_MIN",{"x()":"name","exArgs":1},"out","/ev","^ and ","ev",{"VAR?":"list"},{"VAR?":"list"},"LIST_MIN","-",{"VAR?":"if_empty"},{"f()":".^.^.^"},"out","/ev","\n",{"->":".^.^.^.10"},null]}],["du","ev",1,"==","/ev",{"->":".^.b","c":true},{"b":["pop","\n","ev",{"VAR?":"list"},{"x()":"name","exArgs":1},"out","/ev","\n",{"->":".^.^.^.10"},null]}],["du","ev",0,"==","/ev",{"->":".^.b","c":true},{"b":["pop","\n","ev",{"VAR?":"if_empty"},"out","/ev","\n",{"->":".^.^.^.10"},null]}],[{"->":".^.b"},{"b":["pop","\n","ev",{"VAR?":"list"},"LIST_MIN",{"x()":"name","exArgs":1},"out","/ev","^, ","ev",{"VAR?":"list"},{"VAR?":"list"},"LIST_MIN","-",{"VAR?":"if_empty"},{"f()":".^.^.^"},"out","/ev","\n",{"->":".^.^.^.10"},null]}],"nop","\n",null],"if":[{"temp=":"text"},{"temp=":"cond"},"ev",{"VAR?":"cond"},"/ev",[{"->":".^.b","c":true},{"b":["\n","ev",{"VAR?":"text"},"/ev","~ret",{"->":"if.7"},null]}],[{"->":".^.b"},{"b":["\n","ev","str","^","/str","/ev","~ret",{"->":"if.7"},null]}],"nop","\n",null],"summarize_status":[{"temp=":"person"},"ev",{"VAR?":"person"},{"x()":"name","exArgs":1},"out","/ev","ev",{"VAR?":"person"},{"f()":"total_health"},3,">=","/ev",[{"->":".^.b","c":true},{"b":["^ (risk of death!)",{"->":".^.^.^.13"},null]}],"nop","^: ","ev",{"VAR?":"hungry"},{"VAR?":"person"},"?","str","^hungry,","/str",{"f()":"if"},"out","/ev","^ ","ev",{"VAR?":"starving"},{"VAR?":"person"},"?","str","^starving,","/str",{"f()":"if"},"out","/ev","^ ","ev",{"VAR?":"cold"},{"VAR?":"person"},"?","str","^cold,","/str",{"f()":"if"},"out","/ev","^ ","ev",{"VAR?":"hypothermic"},{"VAR?":"person"},"?","str","^hypothermic,","/str",{"f()":"if"},"out","/ev","^ ","ev",{"VAR?":"tired"},{"VAR?":"person"},"?","str","^tired,","/str",{"f()":"if"},"out","/ev","^ ","ev",{"VAR?":"exhausted"},{"VAR?":"person"},"?","str","^exhausted,","/str",{"f()":"if"},"out","/ev","^ ","ev",{"VAR?":"broken_nose"},{"VAR?":"person"},"?","str","^broken nose,","/str",{"f()":"if"},"out","/ev","^ ","ev",{"VAR?":"broken_leg"},{"VAR?":"person"},"?","str","^broken leg,","/str",{"f()":"if"},"out","/ev","^ ","ev",{"VAR?":"in_pain"},{"VAR?":"person"},"?","str","^in pain,","/str",{"f()":"if"},"out","/ev","^ ","ev",{"VAR?":"terrified"},{"VAR?":"person"},"?","str","^terrified,","/str",{"f()":"if"},"out","/ev","^ ","ev",{"VAR?":"stressed"},{"VAR?":"person"},"?","str","^stressed,","/str",{"f()":"if"},"out","/ev","^ ","ev",{"VAR?":"traumatized"},{"VAR?":"person"},"?","str","^traumatized,","/str",{"f()":"if"},"out","/ev","^ ","ev",{"VAR?":"bruised"},{"VAR?":"person"},"?","str","^bruised,","/str",{"f()":"if"},"out","/ev","^ ","ev",{"VAR?":"agitated"},{"VAR?":"person"},"?","str","^agitated,","/str",{"f()":"if"},"out","/ev","^ ","ev",{"VAR?":"guilty"},{"VAR?":"person"},"?","str","^guilty,","/str",{"f()":"if"},"out","/ev","^ ","ev",{"VAR?":"dysentery"},{"VAR?":"person"},"?","str","^dysentery,","/str",{"f()":"if"},"out","/ev","\n",{"#f":3}],"reset_activities":["ev",false,"/ev",{"VAR=":"ate","re":true},"ev",false,"/ev",{"VAR=":"rested","re":true},"ev",false,"/ev",{"VAR=":"slept","re":true},"ev",false,"/ev",{"VAR=":"played_music","re":true},"ev","void","/ev","->->",null],"activity":[{"eat_meal":[{"temp=":"warm"},"ev",{"VAR?":"warm"},"/ev",[{"->":".^.b","c":true},{"b":["\n","^You eat a hearty meal of warm stew.","\n","ev",{"VAR?":"party"},{"^->":"less_hungry"},{"f()":"for_each"},"pop","/ev","\n","ev",{"VAR?":"party"},{"^->":"less_cold"},{"f()":"for_each"},"pop","/ev","\n","ev",{"VAR?":"party"},{"^->":"maybe_heal"},{"f()":"for_each"},"pop","/ev","\n",{"->":".^.^.^.6"},null]}],[{"->":".^.b"},{"b":["\n","^You eat a meagre meal of cold bread and cheese.","\n","ev",{"VAR?":"party"},{"^->":"less_hungry"},{"f()":"for_each"},"pop","/ev","\n",{"->":".^.^.^.6"},null]}],"nop","\n","ev",true,"/ev",{"VAR=":"ate","re":true},{"->t->":"confirm"},"ev","void","/ev","->->",null],"sleep":[{"temp=":"warm"},"ev",{"VAR?":"warm"},"/ev",[{"->":".^.b","c":true},{"b":["\n","^You spend an unpleasant night tossing and turning.","\n","ev",{"VAR?":"party"},{"^->":"less_cold"},{"f()":"for_each"},"pop","/ev","\n","ev",{"VAR?":"party"},{"^->":"maybe_heal"},{"f()":"for_each"},"pop","/ev","\n",{"->":".^.^.^.6"},null]}],[{"->":".^.b"},{"b":["\n","^You go to sleep shivering.  You wake up even colder.","\n","ev",{"VAR?":"party"},{"^->":"cold_sim"},{"f()":"for_each"},"pop","/ev","\n","ev",{"VAR?":"party"},{"^->":"cold_sim"},{"f()":"for_each"},"pop","/ev","\n",{"->":".^.^.^.6"},null]}],"nop","\n","ev",true,"/ev",{"VAR=":"slept","re":true},"ev",{"VAR?":"party"},{"^->":"less_tired"},{"f()":"for_each"},"pop","/ev","\n","ev",{"VAR?":"party"},{"^->":"less_tired"},{"f()":"for_each"},"pop","/ev","\n",{"->t->":"confirm"},"ev","void","/ev","->->",null],"warm_rest":["^You rest for a while by the fire","\n","ev",{"VAR?":"party"},{"^->":"less_cold"},{"f()":"for_each"},"pop","/ev","\n","ev",{"VAR?":"party"},{"^->":"maybe_heal"},{"f()":"for_each"},"pop","/ev","\n","ev",true,"/ev",{"VAR=":"rested","re":true},{"->t->":"confirm"},"ev","void","/ev","->->",null],"play_harmonica":["^You take a break to play the harmonica and dance, lightening spirits somewhat.","\n","ev",{"VAR?":"party"},{"^->":"cheer_up"},{"f()":"for_each"},"pop","/ev","\n","ev",true,"/ev",{"VAR=":"played_music","re":true},{"->t->":"confirm"},"ev","void","/ev","->->",null],"play_piano":["^You take a break to play the piano and dance, lightening spirits somewhat.","\n","ev",{"VAR?":"party"},{"^->":"cheer_up"},{"f()":"for_each"},"pop","/ev","\n","ev",true,"/ev",{"VAR=":"played_music","re":true},{"->t->":"confirm"},"ev","void","/ev","->->",null]}],"survival_sim":[{"temp=":"people"},"ev",{"VAR?":"people"},{"^->":"check_death"},{"f()":"for_each"},"out","/ev","\n","ev",{"VAR?":"people"},{"VAR?":"dead"},"-",{"^->":"hunger_sim"},{"f()":"for_each"},"out","/ev","\n","ev",{"VAR?":"people"},{"VAR?":"dead"},"-",{"^->":"cold_sim"},{"f()":"for_each"},"out","/ev","\n","ev",{"VAR?":"people"},{"VAR?":"dead"},"-",{"^->":"tired_sim"},{"f()":"for_each"},"out","/ev","\n","ev","void","/ev","~ret",null],"hunger_sim":[{"temp=":"person"},"ev",{"VAR?":"ate"},"!",1,100,"rnd",10,"<=","&&","/ev",[{"->":".^.b","c":true},{"b":["\n","ev",{"VAR?":"person"},{"f()":"more_hungry"},"pop","/ev","\n",{"->":".^.^.^.12"},null]}],"nop","\n","ev","void","/ev","~ret",{"#f":3}],"cold_sim":[{"temp=":"person"},"ev",1,100,"rnd",15,"<=","/ev",[{"->":".^.b","c":true},{"b":["\n","ev",{"VAR?":"person"},{"f()":"more_cold"},"pop","/ev","\n",{"->":".^.^.^.9"},null]}],"nop","\n","ev","void","/ev","~ret",{"#f":3}],"tired_sim":[{"temp=":"person"},"ev",{"VAR?":"rested"},{"VAR?":"slept"},"||","!",1,100,"rnd",10,"<=","&&","/ev",[{"->":".^.b","c":true},{"b":["\n","ev",{"VAR?":"person"},{"f()":"more_tired"},"pop","/ev","\n",{"->":".^.^.^.14"},null]}],"nop","\n","ev","void","/ev","~ret",{"#f":3}],"more_hungry":[{"temp=":"person"},["ev",{"VAR?":"hungry"},{"VAR?":"person"},"?","/ev",{"->":".^.b","c":true},{"b":["\n","ev",{"VAR?":"hungry"},{"VAR?":"person"},"-",{"VAR=":"hungry","re":true},"/ev","ev",{"VAR?":"starving"},{"VAR?":"person"},"+",{"VAR=":"starving","re":true},"/ev","ev",{"VAR?":"person"},{"x()":"name","exArgs":1},"str","^ is now starving!","/str","+",{"VAR?":"bad"},{"f()":"note"},"pop","/ev","\n",{"->":".^.^.^.4"},null]}],["ev",{"VAR?":"starving"},{"VAR?":"person"},"?","/ev",{"->":".^.b","c":true},{"b":["\n","ev","void","/ev","~ret",{"->":".^.^.^.4"},null]}],[{"->":".^.b"},{"b":["\n","ev",{"VAR?":"hungry"},{"VAR?":"person"},"+",{"VAR=":"hungry","re":true},"/ev","ev",{"VAR?":"person"},{"x()":"name","exArgs":1},"str","^ is now hungry.","/str","+",{"VAR?":"bad"},{"f()":"note"},"pop","/ev","\n",{"->":".^.^.^.4"},null]}],"nop","\n",null],"less_hungry":[{"temp=":"person"},["ev",{"VAR?":"hungry"},{"VAR?":"person"},"?","/ev",{"->":".^.b","c":true},{"b":["\n","ev",{"VAR?":"hungry"},{"VAR?":"person"},"-",{"VAR=":"hungry","re":true},"/ev","ev",{"VAR?":"person"},{"x()":"name","exArgs":1},"str","^ is no longer hungry.","/str","+",{"VAR?":"good"},{"f()":"note"},"pop","/ev","\n",{"->":".^.^.^.3"},null]}],["ev",{"VAR?":"starving"},{"VAR?":"person"},"?","/ev",{"->":".^.b","c":true},{"b":["\n","ev",{"VAR?":"starving"},{"VAR?":"person"},"-",{"VAR=":"starving","re":true},"/ev","ev",{"VAR?":"hungry"},{"VAR?":"person"},"+",{"VAR=":"hungry","re":true},"/ev","ev",{"VAR?":"person"},{"x()":"name","exArgs":1},"str","^ is now merely hungry.","/str","+",{"VAR?":"good"},{"f()":"note"},"pop","/ev","\n",{"->":".^.^.^.3"},null]}],"nop","\n",{"#f":3}],"more_tired":[{"temp=":"person"},["ev",{"VAR?":"tired"},{"VAR?":"person"},"?","/ev",{"->":".^.b","c":true},{"b":["\n","ev",{"VAR?":"tired"},{"VAR?":"person"},"-",{"VAR=":"tired","re":true},"/ev","ev",{"VAR?":"exhausted"},{"VAR?":"person"},"+",{"VAR=":"exhausted","re":true},"/ev","ev",{"VAR?":"person"},{"x()":"name","exArgs":1},"str","^ is now exhausted!","/str","+",{"VAR?":"bad"},{"f()":"note"},"pop","/ev","\n",{"->":".^.^.^.4"},null]}],["ev",{"VAR?":"exhausted"},{"VAR?":"person"},"?","/ev",{"->":".^.b","c":true},{"b":["\n","ev","void","/ev","~ret",{"->":".^.^.^.4"},null]}],[{"->":".^.b"},{"b":["\n","ev",{"VAR?":"tired"},{"VAR?":"person"},"+",{"VAR=":"tired","re":true},"/ev","ev",{"VAR?":"person"},{"x()":"name","exArgs":1},"str","^ is now tired.","/str","+",{"VAR?":"bad"},{"f()":"note"},"pop","/ev","\n",{"->":".^.^.^.4"},null]}],"nop","\n",null],"less_tired":[{"temp=":"person"},["ev",{"VAR?":"tired"},{"VAR?":"person"},"?","/ev",{"->":".^.b","c":true},{"b":["\n","ev",{"VAR?":"tired"},{"VAR?":"person"},"-",{"VAR=":"tired","re":true},"/ev","ev",{"VAR?":"person"},{"x()":"name","exArgs":1},"str","^ is no longer tired.","/str","+",{"VAR?":"good"},{"f()":"note"},"pop","/ev","\n",{"->":".^.^.^.3"},null]}],["ev",{"VAR?":"exhausted"},{"VAR?":"person"},"?","/ev",{"->":".^.b","c":true},{"b":["\n","ev",{"VAR?":"exhausted"},{"VAR?":"person"},"-",{"VAR=":"exhausted","re":true},"/ev","ev",{"VAR?":"tired"},{"VAR?":"person"},"+",{"VAR=":"tired","re":true},"/ev","ev",{"VAR?":"person"},{"x()":"name","exArgs":1},"str","^ is now merely tired.","/str","+",{"VAR?":"good"},{"f()":"note"},"pop","/ev","\n",{"->":".^.^.^.3"},null]}],"nop","\n",{"#f":3}],"more_cold":[{"temp=":"person"},["ev",{"VAR?":"cold"},{"VAR?":"person"},"?","/ev",{"->":".^.b","c":true},{"b":["\n","ev",{"VAR?":"cold"},{"VAR?":"person"},"-",{"VAR=":"cold","re":true},"/ev","ev",{"VAR?":"hypothermic"},{"VAR?":"person"},"+",{"VAR=":"hypothermic","re":true},"/ev","ev",{"VAR?":"person"},{"x()":"name","exArgs":1},"str","^ is now hypothermic!","/str","+",{"VAR?":"bad"},{"f()":"note"},"pop","/ev","\n",{"->":".^.^.^.4"},null]}],["ev",{"VAR?":"hypothermic"},{"VAR?":"person"},"?","/ev",{"->":".^.b","c":true},{"b":["\n",{"->":".^.^.^.4"},null]}],[{"->":".^.b"},{"b":["\n","ev",{"VAR?":"cold"},{"VAR?":"person"},"+",{"VAR=":"cold","re":true},"/ev","ev",{"VAR?":"person"},{"x()":"name","exArgs":1},"str","^ is now cold.","/str","+",{"VAR?":"bad"},{"f()":"note"},"pop","/ev","\n",{"->":".^.^.^.4"},null]}],"nop","\n",null],"less_cold":[{"temp=":"person"},["ev",{"VAR?":"cold"},{"VAR?":"person"},"?","/ev",{"->":".^.b","c":true},{"b":["\n","ev",{"VAR?":"cold"},{"VAR?":"person"},"-",{"VAR=":"cold","re":true},"/ev","ev",{"VAR?":"person"},{"x()":"name","exArgs":1},"str","^ is no longer cold.","/str","+",{"VAR?":"good"},{"f()":"note"},"pop","/ev","\n",{"->":".^.^.^.3"},null]}],["ev",{"VAR?":"hypothermic"},{"VAR?":"person"},"?","/ev",{"->":".^.b","c":true},{"b":["\n","ev",{"VAR?":"hypothermic"},{"VAR?":"person"},"-",{"VAR=":"hypothermic","re":true},"/ev","ev",{"VAR?":"cold"},{"VAR?":"person"},"+",{"VAR=":"cold","re":true},"/ev","ev",{"VAR?":"person"},{"x()":"name","exArgs":1},"str","^ is now merely cold.","/str","+",{"VAR?":"good"},{"f()":"note"},"pop","/ev","\n",{"->":".^.^.^.3"},null]}],"nop","\n","ev","void","/ev","~ret",{"#f":3}],"cheer_up":[{"temp=":"person"},"ev",{"VAR?":"terrified"},{"VAR?":"person"},"?",1,100,"rnd",50,"<=","&&","/ev",[{"->":".^.b","c":true},{"b":["\n","ev",{"VAR?":"terrified"},{"VAR?":"person"},"-",{"VAR=":"terrified","re":true},"/ev","ev",{"VAR?":"person"},{"x()":"name","exArgs":1},"str","^ is no longer terrified.","/str","+",{"VAR?":"good"},{"f()":"note"},"pop","/ev","\n",{"->":".^.^.^.13"},null]}],"nop","\n","ev",{"VAR?":"stressed"},{"VAR?":"person"},"?",1,100,"rnd",50,"<=","&&","/ev",[{"->":".^.b","c":true},{"b":["\n","ev",{"VAR?":"stressed"},{"VAR?":"person"},"-",{"VAR=":"stressed","re":true},"/ev","ev",{"VAR?":"person"},{"x()":"name","exArgs":1},"str","^ is no longer stressed.","/str","+",{"VAR?":"good"},{"f()":"note"},"pop","/ev","\n",{"->":".^.^.^.27"},null]}],"nop","\n","ev",{"VAR?":"agitated"},{"VAR?":"person"},"?",1,100,"rnd",50,"<=","&&","/ev",[{"->":".^.b","c":true},{"b":["\n","ev",{"VAR?":"agitated"},{"VAR?":"person"},"-",{"VAR=":"agitated","re":true},"/ev","ev",{"VAR?":"person"},{"x()":"name","exArgs":1},"str","^ is no longer agitated.","/str","+",{"VAR?":"good"},{"f()":"note"},"pop","/ev","\n",{"->":".^.^.^.41"},null]}],"nop","\n","ev",{"VAR?":"guilty"},{"VAR?":"person"},"?",1,100,"rnd",50,"<=","&&","/ev",[{"->":".^.b","c":true},{"b":["\n","ev",{"VAR?":"guilty"},{"VAR?":"person"},"-",{"VAR=":"guilty","re":true},"/ev","ev",{"VAR?":"person"},{"x()":"name","exArgs":1},"str","^ no longer feels guilty.","/str","+",{"VAR?":"good"},{"f()":"note"},"pop","/ev","\n",{"->":".^.^.^.55"},null]}],"nop","\n","ev","void","/ev","~ret",{"#f":3}],"maybe_effect":[{"temp=":"prob"},{"temp=":"effect_name"},{"temp=":"effect"},{"temp=":"people"},"ev",{"VAR?":"people"},"LIST_COUNT",0,"==","/ev",[{"->":".^.b","c":true},{"b":["\n","ev","void","/ev","~ret",{"->":".^.^.^.11"},null]}],"nop","\n","ev",{"VAR?":"people"},"LIST_MIN","/ev",{"temp=":"person"},"\n","ev",1,100,"rnd",{"VAR?":"prob"},"<=",{"VAR?":"effect"},{"VAR?":"person"},"?","!","&&","/ev",[{"->":".^.b","c":true},{"b":["\n","ev",{"VAR?":"effect"},{"VAR?":"person"},"+",{"temp=":"effect","re":true},"/ev","ev",{"VAR?":"person"},{"x()":"name","exArgs":1},"str","^ is now ","/str","+",{"VAR?":"effect_name"},"+",{"VAR?":"bad"},{"f()":"note"},"pop","/ev","\n",{"->":".^.^.^.32"},null]}],"nop","\n","ev",{"VAR?":"people"},{"VAR?":"person"},"-",{"^var":"effect","ci":-1},{"VAR?":"effect_name"},{"VAR?":"prob"},{"f()":".^"},"/ev","~ret","\n",null],"dead_body_seen":["ev",1,100,"rnd",30,"<=","/ev",[{"->":".^.b","c":true},{"b":["\n","ev",{"VAR?":"party"},{"VAR?":"traumatized"},"-",{"f()":"select_from"},"/ev",[{"->":".^.b","c":true},{"b":["\n","ev",{"VAR?":"traumatized"},{"VAR?":"WHO"},"+",{"VAR=":"traumatized","re":true},"/ev","ev",{"VAR?":"WHO"},{"x()":"name","exArgs":1},"str","^ is now traumatized.","/str","+",{"VAR?":"bad"},{"f()":"note"},"pop","/ev","\n",{"->":".^.^.^.8"},null]}],"nop","\n",{"->":".^.^.^.8"},null]}],"nop","\n",null],"maybe_heal":[{"temp=":"person"},"ev",{"VAR?":"broken_nose"},{"VAR?":"person"},"?",1,100,"rnd",5,"<=","&&","/ev",[{"->":".^.b","c":true},{"b":["\n","ev",{"VAR?":"broken_nose"},{"VAR?":"person"},"-",{"VAR=":"broken_nose","re":true},"/ev","ev",{"VAR?":"person"},{"x()":"name","exArgs":1},"str","^'s broken nose has healed.","/str","+",{"VAR?":"good"},{"f()":"note"},"pop","/ev","\n",{"->":".^.^.^.13"},null]}],"nop","\n","ev",{"VAR?":"broken_leg"},{"VAR?":"person"},"?",1,100,"rnd",5,"<=","&&","/ev",[{"->":".^.b","c":true},{"b":["\n","ev",{"VAR?":"broken_leg"},{"VAR?":"person"},"-",{"VAR=":"broken_leg","re":true},"/ev","ev",{"VAR?":"person"},{"x()":"name","exArgs":1},"str","^'s broken leg has healed.","/str","+",{"VAR?":"good"},{"f()":"note"},"pop","/ev","\n",{"->":".^.^.^.27"},null]}],"nop","\n","ev",{"VAR?":"dysentery"},{"VAR?":"person"},"?",1,100,"rnd",5,"<=","&&","/ev",[{"->":".^.b","c":true},{"b":["\n","ev",{"VAR?":"dysentery"},{"VAR?":"person"},"-",{"VAR=":"dysentery","re":true},"/ev","ev",{"VAR?":"person"},{"x()":"name","exArgs":1},"str","^ no longer has dysentery","/str","+",{"VAR?":"good"},{"f()":"note"},"pop","/ev","\n",{"->":".^.^.^.41"},null]}],"nop","\n",{"#f":3}],"total_health":[{"temp=":"person"},"ev",0,"/ev",{"temp=":"health_score"},"ev",{"VAR?":"dysentery"},{"VAR?":"person"},"?","/ev",[{"->":".^.b","c":true},{"b":["\n","ev",{"VAR?":"health_score"},2,"+",{"temp=":"health_score","re":true},"/ev",{"->":".^.^.^.11"},null]}],"nop","\n","ev",{"VAR?":"broken_leg"},{"VAR?":"person"},"?","/ev",[{"->":".^.b","c":true},{"b":["\n","ev",{"VAR?":"health_score"},2,"+",{"temp=":"health_score","re":true},"/ev",{"->":".^.^.^.19"},null]}],"nop","\n","ev",{"VAR?":"hypothermic"},{"VAR?":"person"},"?","/ev",[{"->":".^.b","c":true},{"b":["\n","ev",{"VAR?":"health_score"},1.5,"+",{"temp=":"health_score","re":true},"/ev",{"->":".^.^.^.27"},null]}],"nop","\n","ev",{"VAR?":"exhausted"},{"VAR?":"person"},"?","/ev",[{"->":".^.b","c":true},{"b":["\n","ev",{"VAR?":"health_score"},1,"+",{"temp=":"health_score","re":true},"/ev",{"->":".^.^.^.35"},null]}],"nop","\n","ev",{"VAR?":"starving"},{"VAR?":"person"},"?","/ev",[{"->":".^.b","c":true},{"b":["\n","ev",{"VAR?":"health_score"},1,"+",{"temp=":"health_score","re":true},"/ev",{"->":".^.^.^.43"},null]}],"nop","\n","ev",{"VAR?":"broken_nose"},{"VAR?":"person"},"?","/ev",[{"->":".^.b","c":true},{"b":["\n","ev",{"VAR?":"health_score"},1,"+",{"temp=":"health_score","re":true},"/ev",{"->":".^.^.^.51"},null]}],"nop","\n","ev",{"VAR?":"in_pain"},{"VAR?":"person"},"?","/ev",[{"->":".^.b","c":true},{"b":["\n","ev",{"VAR?":"health_score"},1,"+",{"temp=":"health_score","re":true},"/ev",{"->":".^.^.^.59"},null]}],"nop","\n","ev",{"VAR?":"traumatized"},{"VAR?":"person"},"?","/ev",[{"->":".^.b","c":true},{"b":["\n","ev",{"VAR?":"health_score"},1,"+",{"temp=":"health_score","re":true},"/ev",{"->":".^.^.^.67"},null]}],"nop","\n","ev",{"VAR?":"terrified"},{"VAR?":"person"},"?","/ev",[{"->":".^.b","c":true},{"b":["\n","ev",{"VAR?":"health_score"},1,"+",{"temp=":"health_score","re":true},"/ev",{"->":".^.^.^.75"},null]}],"nop","\n","ev",{"VAR?":"stressed"},{"VAR?":"person"},"?","/ev",[{"->":".^.b","c":true},{"b":["\n","ev",{"VAR?":"health_score"},1,"+",{"temp=":"health_score","re":true},"/ev",{"->":".^.^.^.83"},null]}],"nop","\n","ev",{"VAR?":"agitated"},{"VAR?":"person"},"?","/ev",[{"->":".^.b","c":true},{"b":["\n","ev",{"VAR?":"health_score"},1,"+",{"temp=":"health_score","re":true},"/ev",{"->":".^.^.^.91"},null]}],"nop","\n","ev",{"VAR?":"bruised"},{"VAR?":"person"},"?","/ev",[{"->":".^.b","c":true},{"b":["\n","ev",{"VAR?":"health_score"},1,"+",{"temp=":"health_score","re":true},"/ev",{"->":".^.^.^.99"},null]}],"nop","\n","ev",{"VAR?":"guilty"},{"VAR?":"person"},"?","/ev",[{"->":".^.b","c":true},{"b":["\n","ev",{"VAR?":"health_score"},0.5,"+",{"temp=":"health_score","re":true},"/ev",{"->":".^.^.^.107"},null]}],"nop","\n","ev",{"VAR?":"health_score"},"/ev","~ret",null],"check_death":[{"temp=":"person"},"ev",{"VAR?":"person"},{"f()":"total_health"},"/ev",{"temp=":"health"},"\n","ev",false,"/ev",{"temp=":"died"},["ev",{"VAR?":"health"},5,">=","/ev",{"->":".^.b","c":true},{"b":["\n","ev",1,100,"rnd",100,"<=","/ev",{"temp=":"died","re":true},"\n",{"->":".^.^.^.13"},null]}],["ev",{"VAR?":"health"},3,">=","/ev",{"->":".^.b","c":true},{"b":["\n","ev",1,100,"rnd",20,"<=","/ev",{"temp=":"died","re":true},"\n",{"->":".^.^.^.13"},null]}],"nop","\n","ev",{"VAR?":"died"},"/ev",[{"->":".^.b","c":true},{"b":["\n","ev",{"VAR?":"person"},{"f()":"death_message"},"out","/ev","^ ",{"#":"bad"},{"#":"severe"},"\n","ev",{"VAR?":"person"},{"f()":"kill"},"pop","/ev","\n",{"->":".^.^.^.19"},null]}],"nop","\n",{"#f":3}],"death_message":[{"temp=":"person"},{"#":"bad"},["ev",{"VAR?":"dysentery"},{"VAR?":"person"},"?","/ev",{"->":".^.b","c":true},{"b":["\n","ev",{"VAR?":"person"},{"x()":"name","exArgs":1},"str","^ has died of dysentery.","/str","+","/ev","~ret","\n",{"->":".^.^.^.13"},null]}],["ev",{"VAR?":"hypothermic"},{"VAR?":"person"},"?","/ev",{"->":".^.b","c":true},{"b":["\n","ev",{"VAR?":"person"},{"x()":"name","exArgs":1},"str","^ has died of hypothermia.","/str","+","/ev","~ret","\n",{"->":".^.^.^.13"},null]}],["ev",{"VAR?":"broken_leg"},{"VAR?":"person"},"?","/ev",{"->":".^.b","c":true},{"b":["\n","ev",{"VAR?":"person"},{"x()":"name","exArgs":1},"str","^ has died of complications from their broken leg.","/str","+","/ev","~ret","\n",{"->":".^.^.^.13"},null]}],["ev",{"VAR?":"exhausted"},{"VAR?":"person"},"?","/ev",{"->":".^.b","c":true},{"b":["\n","ev",{"VAR?":"person"},{"x()":"name","exArgs":1},"str","^ has died of exhaustion.","/str","+","/ev","~ret","\n",{"->":".^.^.^.13"},null]}],["ev",{"VAR?":"broken_nose"},{"VAR?":"person"},"?","/ev",{"->":".^.b","c":true},{"b":["\n","ev",{"VAR?":"person"},{"x()":"name","exArgs":1},"str","^ has died of complications from their broken nose.","/str","+","/ev","~ret","\n",{"->":".^.^.^.13"},null]}],["ev",{"VAR?":"traumatized"},{"VAR?":"person"},"?","/ev",{"->":".^.b","c":true},{"b":["\n","ev",{"VAR?":"person"},{"x()":"name","exArgs":1},"str","^ couldn't handle it.  They ran off into the night, never to be seen again.","/str","+","/ev","~ret","\n",{"->":".^.^.^.13"},null]}],["ev",{"VAR?":"terrified"},{"VAR?":"person"},"?","/ev",{"->":".^.b","c":true},{"b":["\n","ev",{"VAR?":"person"},{"x()":"name","exArgs":1},"str","^ has died from sheer terror.","/str","+","/ev","~ret","\n",{"->":".^.^.^.13"},null]}],["ev",{"VAR?":"in_pain"},{"VAR?":"person"},"?","/ev",{"->":".^.b","c":true},{"b":["\n","ev",{"VAR?":"person"},{"x()":"name","exArgs":1},"str","^ has died from sheer pain.","/str","+","/ev","~ret","\n",{"->":".^.^.^.13"},null]}],["ev",{"VAR?":"starving"},{"VAR?":"person"},"?","/ev",{"->":".^.b","c":true},{"b":["\n","ev",{"VAR?":"person"},{"x()":"name","exArgs":1},"str","^ has died of malnutrition.","/str","+","/ev","~ret","\n",{"->":".^.^.^.13"},null]}],["ev",{"VAR?":"stressed"},{"VAR?":"person"},"?",{"VAR?":"agitated"},{"VAR?":"person"},"?","||","/ev",{"->":".^.b","c":true},{"b":["\n","ev",{"VAR?":"person"},{"x()":"name","exArgs":1},"str","^ has died of a heart attack.  The stress was just too much for them.","/str","+","/ev","~ret","\n",{"->":".^.^.^.13"},null]}],[{"->":".^.b"},{"b":["\n","ev","str","^Sadly, ","/str",{"VAR?":"person"},{"x()":"name","exArgs":1},"+","str","^ has died of their many ailments.","/str","+","/ev","~ret","\n",{"->":".^.^.^.13"},null]}],"nop","\n",null],"kill":[{"temp=":"person"},"ev",{"VAR?":"dead"},{"VAR?":"person"},"+",{"VAR=":"dead","re":true},"/ev","ev",{"VAR?":"party"},{"VAR?":"person"},"-",{"VAR=":"party","re":true},"/ev",null],"check_blocking_encounters":["ev",{"VAR?":"current_location"},{"VAR?":"bear_roadhouse"},"==",{"CNT?":"bear_attack"},"!","&&","/ev",[{"->":".^.b","c":true},{"b":["\n","ev",{"^->":"choose_next_destination"},{"^->":"roadhouse"},"/ev",{"->":"bear_attack"},{"->":".^.^.^.9"},null]}],"nop","\n","ev","void","/ev","->->",null],"get_additional_encounters":[{"temp=":"back"},"ev",{"VAR?":"current_location"},{"VAR?":"old_man_roadhouse"},"==","/ev",[{"->":".^.b","c":true},{"b":["\n","ev",{"VAR?":"back"},"/ev","thread",{"->":"angry_old_man"},{"->":".^.^.^.7"},null]}],"nop","\n","ev",{"VAR?":"current_location"},{"VAR?":"gambling_roadhouse"},"==","/ev",[{"->":".^.b","c":true},{"b":["\n","ev",{"VAR?":"back"},"/ev","thread",{"->":"gamblers"},{"->":".^.^.^.15"},null]}],"nop","\n","ev",{"VAR?":"current_location"},{"VAR?":"last_roadhouse"},"==","/ev",[{"->":".^.b","c":true},{"b":["\n","^This is the last place to rest before your final destination.","\n",{"->":".^.^.^.23"},null]}],"nop","\n","done",null],"roadhouse_arrival":[{"->t->":"reset_activities"},{"->t->":"check_blocking_encounters"},"ev",1,100,"rnd",50,"<=","/ev",{"VAR=":"fire_lit","re":true},"\n","ev",1,100,"rnd",50,"<=","/ev",{"VAR=":"has_bed","re":true},"\n","ev",1,100,"rnd",50,"<=","/ev",{"VAR=":"has_piano","re":true},"\n","ev",{"VAR?":"current_location"},{"VAR?":"bear_roadhouse"},"==","/ev",[{"->":".^.b","c":true},{"b":["\n","ev",false,"/ev",{"VAR=":"fire_lit","re":true},{"->":".^.^.^.35"},null]}],"nop","\n","^You arrive at a small roadhouse.","\n",{"->t->":"confirm"},{"->":"roadhouse"},null],"roadhouse":[[[{"#":"CLEAR"},"ev",{"VAR?":"fire_lit"},"/ev",[{"->":".^.b","c":true},{"b":["^A fire crackles in the fireplace.",{"->":".^.^.^.6"},null]}],[{"->":".^.b"},{"b":["^The fireplace is unlit and the room is cold and damp.",{"->":".^.^.^.6"},null]}],"nop","^  ","ev",{"VAR?":"has_bed"},"/ev",[{"->":".^.b","c":true},{"b":["^ This room is equipped with adequate bedding for your whole party.",{"->":".^.^.^.12"},null]}],"nop","^  ","ev",{"VAR?":"has_piano"},"/ev",[{"->":".^.b","c":true},{"b":["^ There is ",["ev","visit",1,"MIN","/ev","ev","du",0,"==","/ev",{"->":".^.s0","c":true},"ev","du",1,"==","/ev",{"->":".^.s1","c":true},"nop",{"s0":["pop","^a tack piano",{"->":".^.^.17"},null],"s1":["pop","^an upright piano",{"->":".^.^.17"},null],"#f":5}],"^ in the corner of the room.",{"->":".^.^.^.18"},null]}],"nop","\n","ev",{"^->":"roadhouse.0.options"},"/ev","thread",{"->":"standard_menu_options"},"ev",{"^->":"roadhouse.0.options"},"/ev","thread",{"->":"get_additional_encounters"},"ev","str","^Light a fire. (1 hour)","/str",{"VAR?":"fire_lit"},"!","/ev",{"*":".^.c-0","flg":5},"ev","str","^Rest by the fire. (1 hour)","/str",{"VAR?":"fire_lit"},"/ev",{"*":".^.c-1","flg":5},"ev","str","^Eat a cold meal. (1 hour)","/str",{"VAR?":"ate"},"!","/ev",{"*":".^.c-2","flg":5},"ev","str","^Eat a warm meal. (2 hours)","/str",{"VAR?":"ate"},"!",{"VAR?":"fire_lit"},"&&","/ev",{"*":".^.c-3","flg":5},"ev","str","^Get a good night's sleep. (6 hours)","/str",{"VAR?":"slept"},"!",{"VAR?":"has_bed"},"&&","/ev",{"*":".^.c-4","flg":5},"ev","str","^Get a good night's sleep (using bedroll). (6 hours)","/str",{"VAR?":"slept"},"!",{"VAR?":"inventory"},{"VAR?":"bedroll"},"?","&&",{"VAR?":"has_bed"},"!","&&","/ev",{"*":".^.c-5","flg":5},"ev","str","^Play the harmonica. (1 hour)","/str",{"VAR?":"played_music"},"!",{"VAR?":"inventory"},{"VAR?":"harmonica"},"?","&&",{"VAR?":"has_piano"},"!","&&","/ev",{"*":".^.c-6","flg":5},"ev","str","^Play the piano. (1 hour)","/str",{"VAR?":"played_music"},"!",{"VAR?":"has_piano"},"&&","/ev",{"*":".^.c-7","flg":5},"ev","str","^Get back on the road.","/str","/ev",{"*":".^.c-8","flg":4},{"c-0":["\n","^After spending some time chopping wood you are able to light a fire in the fireplace.","\n","ev",true,"/ev",{"VAR=":"fire_lit","re":true},"ev",{"VAR?":"hours_remaining"},1,"-",{"VAR=":"hours_remaining","re":true},"/ev",{"->t->":"confirm"},{"->":".^.^.^.g-0"},null],"c-1":["\n",{"->t->":"activity.warm_rest"},"ev",{"VAR?":"hours_remaining"},1,"-",{"VAR=":"hours_remaining","re":true},"/ev",{"->":".^.^.^.g-0"},null],"c-2":["\n","ev",false,"/ev",{"->t->":"activity.eat_meal"},"ev",{"VAR?":"hours_remaining"},1,"-",{"VAR=":"hours_remaining","re":true},"/ev",{"->":".^.^.^.g-0"},null],"c-3":["\n","ev",true,"/ev",{"->t->":"activity.eat_meal"},"ev",{"VAR?":"hours_remaining"},2,"-",{"VAR=":"hours_remaining","re":true},"/ev",{"->":".^.^.^.g-0"},null],"c-4":["\n","ev",{"VAR?":"fire_lit"},"/ev",{"->t->":"activity.sleep"},"ev",{"VAR?":"hours_remaining"},6,"-",{"VAR=":"hours_remaining","re":true},"/ev",{"->":".^.^.^.g-0"},null],"c-5":["\n","ev",{"VAR?":"fire_lit"},"/ev",{"->t->":"activity.sleep"},"ev",{"VAR?":"hours_remaining"},6,"-",{"VAR=":"hours_remaining","re":true},"/ev",{"->":".^.^.^.g-0"},null],"c-6":["\n",{"->t->":"activity.play_harmonica"},"ev",{"VAR?":"hours_remaining"},1,"-",{"VAR=":"hours_remaining","re":true},"/ev",{"->":".^.^.^.g-0"},null],"c-7":["\n",{"->t->":"activity.play_piano"},"ev",{"VAR?":"hours_remaining"},1,"-",{"VAR=":"hours_remaining","re":true},"/ev",{"->":".^.^.^.g-0"},null],"c-8":["\n",{"->":"choose_next_destination"},{"->":".^.^.^.g-0"},null],"#f":7,"#n":"options"}],{"g-0":[{"->":".^.^.options"},null]}],{"#f":3}],"name":[{"temp=":"person"},"ev",{"VAR?":"person"},"/ev",["du","ev",{"VAR?":"p1"},"==","/ev",{"->":".^.b","c":true},{"b":["pop","\n","ev","str","^Alice","/str","/ev","~ret",{"->":"name.9"},null]}],["du","ev",{"VAR?":"p2"},"==","/ev",{"->":".^.b","c":true},{"b":["pop","\n","ev","str","^Bob","/str","/ev","~ret",{"->":"name.9"},null]}],["du","ev",{"VAR?":"p3"},"==","/ev",{"->":".^.b","c":true},{"b":["pop","\n","ev","str","^Charlie","/str","/ev","~ret",{"->":"name.9"},null]}],["du","ev",{"VAR?":"p4"},"==","/ev",{"->":".^.b","c":true},{"b":["pop","\n","ev","str","^Devon","/str","/ev","~ret",{"->":"name.9"},null]}],"pop","nop","\n",null],"risk_of_death":[{"temp=":"person_str"},"ev",{"VAR?":"p1"},"/ev",{"temp=":"person"},"ev",{"VAR?":"person_str"},"/ev",["du","ev","str","^p1","/str","==","/ev",{"->":".^.b","c":true},{"b":["pop","\n","ev",{"VAR?":"p1"},"/ev",{"temp=":"person","re":true},{"->":".^.^.^.13"},null]}],["du","ev","str","^p2","/str","==","/ev",{"->":".^.b","c":true},{"b":["pop","\n","ev",{"VAR?":"p2"},"/ev",{"temp=":"person","re":true},{"->":".^.^.^.13"},null]}],["du","ev","str","^p3","/str","==","/ev",{"->":".^.b","c":true},{"b":["pop","\n","ev",{"VAR?":"p3"},"/ev",{"temp=":"person","re":true},{"->":".^.^.^.13"},null]}],["du","ev","str","^p4","/str","==","/ev",{"->":".^.b","c":true},{"b":["pop","\n","ev",{"VAR?":"p4"},"/ev",{"temp=":"person","re":true},{"->":".^.^.^.13"},null]}],"pop","nop","\n","ev",{"VAR?":"person"},{"f()":"total_health"},3,">=","/ev","~ret","\n",{"#":"Some other notes about API stuff:"},{"#":"- Options formatted like ((this)) are not displayed to player"},{"#":"- Tags"},{"#":"good, bad, severe control text display"},{"#":"- currently_moving and weather are observed by the engine"},null],"choose_next_destination":[{"#":"CLEAR"},"ev",true,"/ev",{"VAR=":"currently_moving","re":true},"^You head ",["ev","visit",1,"MIN","/ev","ev","du",0,"==","/ev",{"->":".^.s0","c":true},"ev","du",1,"==","/ev",{"->":".^.s1","c":true},"nop",{"s0":["pop","^out",{"->":".^.^.17"},null],"s1":["pop","^back out",{"->":".^.^.17"},null],"#f":5}],"^ into the endless night.","\n","^Where to next?","\n","ev",{"VAR?":"current_location"},"/ev",["du","ev",{"VAR?":"debug_location"},"==","/ev",{"->":".^.b","c":true},{"b":["pop","\n","ev","str","^old man","/str","/ev",{"*":".^.c-0","flg":4},"ev","str","^gambling","/str","/ev",{"*":".^.c-1","flg":4},"ev","str","^missing roadhouse","/str","/ev",{"*":".^.c-2","flg":4},"ev","str","^bear roadhouse","/str","/ev",{"*":".^.c-3","flg":4},"ev","str","^rh1","/str","/ev",{"*":".^.c-4","flg":4},"ev","str","^rh2","/str","/ev",{"*":".^.c-5","flg":4},"ev","str","^last_roadhouse","/str","/ev",{"*":".^.c-6","flg":4},{"->":".^.^.^.27"},{"c-0":["\n","ev",0,{"VAR?":"old_man_roadhouse"},"/ev",{"->":"traveling_loop"},null],"c-1":["\n","ev",0,{"VAR?":"gambling_roadhouse"},"/ev",{"->":"traveling_loop"},null],"c-2":["\n","ev",0,{"VAR?":"missing_roadhouse"},"/ev",{"->":"traveling_loop"},null],"c-3":["\n","ev",0,{"VAR?":"bear_roadhouse"},"/ev",{"->":"traveling_loop"},null],"c-4":["\n","ev",0,{"VAR?":"rh1"},"/ev",{"->":"traveling_loop"},null],"c-5":["\n","ev",0,{"VAR?":"rh2"},"/ev",{"->":"traveling_loop"},null],"c-6":["\n","ev",0,{"VAR?":"last_roadhouse"},"/ev",{"->":"traveling_loop"},null]}]}],["du","ev",{"VAR?":"start_location"},"==","/ev",{"->":".^.b","c":true},{"b":["pop","\n","ev","str","^First roadhouse (4 hours)","/str","/ev",{"*":".^.c-0","flg":4},{"->":".^.^.^.27"},{"c-0":["\n","ev",2,{"VAR?":"rh1"},"/ev",{"->":"traveling_loop"},null]}]}],["du","ev",{"VAR?":"rh1"},"==","/ev",{"->":".^.b","c":true},{"b":["pop","\n","ev","str","^Next roadhouse (6 hours)","/str","/ev",{"*":".^.c-0","flg":4},{"->":".^.^.^.27"},{"c-0":["^   ","\n","ev",3,{"VAR?":"rh2"},"/ev",{"->":"traveling_loop"},null]}]}],["du","ev",{"VAR?":"rh2"},"==","/ev",{"->":".^.b","c":true},{"b":["pop","\n","ev","str","^Miser's Valley (6 hours)","/str","/ev",{"*":".^.c-0","flg":4},"ev","str","^Gamblers' Gulch (6 hours)","/str","/ev",{"*":".^.c-1","flg":4},{"->":".^.^.^.27"},{"c-0":["^   ","\n","ev",3,{"VAR?":"old_man_roadhouse"},"/ev",{"->":"traveling_loop"},null],"c-1":["^   ","\n","ev",3,{"VAR?":"gambling_roadhouse"},"/ev",{"->":"traveling_loop"},null]}]}],["du","ev",{"VAR?":"old_man_roadhouse"},"==","/ev",{"->":".^.b","c":true},{"b":["pop","\n","ev","str","^Next roadhouse (6 hours)","/str","/ev",{"*":".^.c-0","flg":4},{"->":".^.^.^.27"},{"c-0":["^   ","\n","ev",3,{"VAR?":"rh3"},"/ev",{"->":"traveling_loop"},null]}]}],["du","ev",{"VAR?":"gambling_roadhouse"},"==","/ev",{"->":".^.b","c":true},{"b":["pop","\n","ev","str","^Next roadhouse (6 hours)","/str","/ev",{"*":".^.c-0","flg":4},{"->":".^.^.^.27"},{"c-0":["^   ","\n","ev",3,{"VAR?":"rh3"},"/ev",{"->":"traveling_loop"},null]}]}],["du","ev",{"VAR?":"rh3"},"==","/ev",{"->":".^.b","c":true},{"b":["pop","\n","ev","str","^Next roadhouse (6 hours)","/str","/ev",{"*":".^.c-0","flg":4},{"->":".^.^.^.27"},{"c-0":["^   ","\n","ev",3,{"VAR?":"bear_roadhouse"},"/ev",{"->":"traveling_loop"},null]}]}],["du","ev",{"VAR?":"missing_roadhouse"},"==","/ev",{"->":".^.b","c":true},{"b":["pop","\n","ev","str","^Next roadhouse (6 hours)","/str","/ev",{"*":".^.c-0","flg":4},{"->":".^.^.^.27"},{"c-0":["^   ","\n","ev",3,{"VAR?":"rh4"},"/ev",{"->":"traveling_loop"},null]}]}],["du","ev",{"VAR?":"bear_roadhouse"},"==","/ev",{"->":".^.b","c":true},{"b":["pop","\n","ev","str","^Next roadhouse (6 hours)","/str","/ev",{"*":".^.c-0","flg":4},{"->":".^.^.^.27"},{"c-0":["^   ","\n","ev",3,{"VAR?":"rh4"},"/ev",{"->":"traveling_loop"},null]}]}],["du","ev",{"VAR?":"rh4"},"==","/ev",{"->":".^.b","c":true},{"b":["pop","\n","ev","str","^Last roadhouse (6 hours)","/str","/ev",{"*":".^.c-0","flg":4},{"->":".^.^.^.27"},{"c-0":["^   ","\n","ev",3,{"VAR?":"last_roadhouse"},"/ev",{"->":"traveling_loop"},null]}]}],["du","ev",{"VAR?":"last_roadhouse"},"==","/ev",{"->":".^.b","c":true},{"b":["pop","\n","ev","str","^10 hours to final destination","/str","/ev",{"*":".^.c-0","flg":4},{"->":".^.^.^.27"},{"c-0":["^   ","\n","ev",5,{"VAR?":"final_destination"},"/ev",{"->":"traveling_loop"},null]}]}],["du","ev",{"VAR?":"final_destination"},"==","/ev",{"->":".^.b","c":true},{"b":["pop","\n","ev","str","^Deliver the serum!","/str","/ev",{"*":".^.c-0","flg":4},{"->":".^.^.^.27"},{"c-0":["\n",{"->":"endings.win"},null]}]}],"pop","nop","\n",{"#f":3}],"traveling_loop":[{"temp=":"destination"},{"temp=":"turns_to_destination"},["ev",true,"/ev",{"VAR=":"currently_moving","re":true},{"#":"CLEAR"},{"->t->":"random_event"},{"->t->":"process_weather"},{"#":"CLEAR"},"ev",{"VAR?":"party"},{"f()":"survival_sim"},"out","/ev","\n","ev",{"VAR?":"turns_to_destination"},0,"==","/ev",[{"->":".^.b","c":true},{"b":["\n","ev",false,"/ev",{"VAR=":"currently_moving","re":true},"ev",{"VAR?":"destination"},"/ev",{"VAR=":"current_location","re":true},"ev",{"VAR?":"current_location"},{"VAR?":"final_destination"},"==","/ev",[{"->":".^.b","c":true},{"b":["\n",{"->":"endings.win"},{"->":".^.^.^.16"},null]}],[{"->":".^.b"},{"b":["\n",{"->":"roadhouse_arrival"},{"->":".^.^.^.16"},null]}],"nop","\n",{"->":".^.^.^.20"},null]}],"nop","\n","ev",{"VAR?":"hours_remaining"},2,"-",{"VAR=":"hours_remaining","re":true},"/ev",{"->t->":"check_loss"},[["ev","visit",5,"seq","/ev","ev","du",0,"==","/ev",{"->":".^.s0","c":true},"ev","du",1,"==","/ev",{"->":".^.s1","c":true},"ev","du",2,"==","/ev",{"->":".^.s2","c":true},"ev","du",3,"==","/ev",{"->":".^.s3","c":true},"ev","du",4,"==","/ev",{"->":".^.s4","c":true},"nop",{"s0":["pop","^You continue past miles of inhospitable landscape.",{"->":".^.^.35"},null],"s1":["pop","^The harsh and unforgiving landscape rushes past as you continue on your way.",{"->":".^.^.35"},null],"s2":["pop","^Imposing scenery passes you by; it's too cold for you to appreciate the hostile beauty of the Arctic.",{"->":".^.^.35"},null],"s3":["pop","^There isn't a breath in this land of death as you hurry, horror-driven.",{"->":".^.^.35"},null],"s4":["pop","^There is no sound but the heavy breathing of the dogs.",{"->":".^.^.35"},null],"#f":5}],"\n",{"->t->":"describe_weather"},"^Only ","ev",{"VAR?":"hours_remaining"},"out","/ev","^ hours remain.","\n","ev",{"^->":"traveling_loop.2.options"},"/ev","thread",{"->":"standard_menu_options"},"ev","str","^Continue...","/str","/ev",{"*":".^.c-0","flg":4},{"c-0":["\n",{"->":".^.^.^.g-0"},null],"#f":7,"#n":"options"}],{"g-0":["ev",{"VAR?":"turns_to_destination"},1,"-",{"VAR?":"destination"},"/ev",{"->":".^.^.^"},null]}],null],"angry_old_man":[{"temp=":"next"},["^You are not alone here. ","<>","\n","ev",{"VAR?":"knocked_out_old_man"},"/ev",[{"->":".^.b","c":true},{"b":["\n","^The old man is still lying, unconscious, in the corner.","\n",{"->":".^.^.^.8"},null]}],[{"->":".^.b"},{"b":["\n",["ev","visit",1,"MIN","/ev","ev","du",0,"==","/ev",{"->":".^.s0","c":true},"ev","du",1,"==","/ev",{"->":".^.s1","c":true},"nop",{"s0":["pop","^You notice a bearded old man eating at a table in the corner.",{"->":".^.^.17"},null],"s1":["pop","^The old man is still sitting in the corner, ignoring you.",{"->":".^.^.17"},null],"#f":5}],"\n",{"->":".^.^.^.8"},null]}],"nop","\n","ev","str","^Loot the old man's belongings.","/str",{"VAR?":"knocked_out_old_man"},"/ev",{"*":".^.c-0","flg":21},"ev","str","^Approach the old man.","/str","/ev",{"*":".^.c-1","flg":20},{"c-0":["\n","ev",{"VAR?":"items"},"LIST_ALL",{"VAR?":"inventory"},"-","/ev",{"temp=":"possible_loot"},"\n","ev",{"VAR?":"possible_loot"},"LIST_COUNT",0,">","/ev",[{"->":".^.b","c":true},{"b":["\n","ev",{"VAR?":"possible_loot"},"lrnd","/ev",{"temp=":"found"},"\n","^You take a ","ev",{"VAR?":"found"},"out","/ev","^ from the man's unconscious body.","\n","ev",{"VAR?":"inventory"},{"VAR?":"found"},"+",{"VAR=":"inventory","re":true},"/ev","ev",{"VAR?":"party"},{"VAR?":"guilty"},"-",{"f()":"select_from"},"/ev",[{"->":".^.b","c":true},{"b":["\n","ev",{"VAR?":"guilty"},{"VAR?":"WHO"},"+",{"VAR=":"guilty","re":true},"/ev","ev",{"VAR?":"WHO"},{"x()":"name","exArgs":1},"out","/ev","^ feels guilty about this. ",{"#":"bad"},"\n",{"->":".^.^.^.27"},null]}],"nop","\n",{"->":".^.^.^.17"},null]}],[{"->":".^.b"},{"b":["\n","^You don't find anything of value.","\n",{"->":".^.^.^.17"},null]}],"nop","\n",{"->t->":"confirm"},{"->":"next","var":true},{"#f":5}],"c-1":["\n","^You approach the old man.  He glares at you.","\n","^\"What are you doing around here?\"","\n",[["ev",{"^->":"angry_old_man.1.c-1.5.0.$r1"},{"temp=":"$r"},"str",{"->":".^.s"},[{"#n":"$r1"}],"/str","/ev",{"*":".^.^.c-0","flg":18},{"s":["^\"None of your business.\"",{"->":"$r","var":true},null]}],["ev",{"^->":"angry_old_man.1.c-1.5.1.$r1"},{"temp=":"$r"},"str",{"->":".^.s"},[{"#n":"$r1"}],"/str","/ev",{"*":".^.^.c-1","flg":18},{"s":["^\"Delivering diptheria serum to avert an epidemic.\"",{"->":"$r","var":true},null]}],{"c-0":["ev",{"^->":"angry_old_man.1.c-1.5.c-0.$r2"},"/ev",{"temp=":"$r"},{"->":".^.^.0.s"},[{"#n":"$r2"}],"\n","^The old man snorts. \"Why are you talking to me, then?\"","\n",[["ev",{"^->":"angry_old_man.1.c-1.5.c-0.9.0.$r1"},{"temp=":"$r"},"str",{"->":".^.s"},[{"#n":"$r1"}],"/str","/ev",{"*":".^.^.c-0","flg":18},{"s":["^\"Just trying to be friendly.\"",{"->":"$r","var":true},null]}],["ev",{"^->":"angry_old_man.1.c-1.5.c-0.9.1.$r1"},{"temp=":"$r"},"str",{"->":".^.s"},[{"#n":"$r1"}],"/str","/ev",{"*":".^.^.c-1","flg":18},{"s":["^\"I'm not sure, to be honest.\"",{"->":"$r","var":true},null]}],{"c-0":["ev",{"^->":"angry_old_man.1.c-1.5.c-0.9.c-0.$r2"},"/ev",{"temp=":"$r"},{"->":".^.^.0.s"},[{"#n":"$r2"}],"\n","^\"Well, you're not, so stop trying.\" ","<>","\n",{"->":".^.^.g-0"},{"#f":5}],"c-1":["ev",{"^->":"angry_old_man.1.c-1.5.c-0.9.c-1.$r2"},"/ev",{"temp=":"$r"},{"->":".^.^.1.s"},[{"#n":"$r2"}],"\n","^\"Then leave me alone.\" ","<>","\n",{"->":".^.^.g-0"},{"#f":5}],"g-0":["^The old man goes back to his meal.","\n",{"->t->":"confirm"},{"->":"next","var":true},{"->":".^.^.^.^.g-0"},null]}],{"#f":5}],"c-1":["ev",{"^->":"angry_old_man.1.c-1.5.c-1.$r2"},"/ev",{"temp=":"$r"},{"->":".^.^.1.s"},[{"#n":"$r2"}],"\n",{"->":".^.^.g-0"},{"#f":5}],"g-0":["^The man seems unimpressed.  \"Why would you do that?\"","\n",["ev",{"^->":"angry_old_man.1.c-1.5.g-0.2.$r1"},{"temp=":"$r"},"str",{"->":".^.s"},[{"#n":"$r1"}],"/str","/ev",{"*":".^.^.c-2","flg":18},{"s":["^\"To make a name for myself.\"",{"->":"$r","var":true},null]}],["ev",{"^->":"angry_old_man.1.c-1.5.g-0.3.$r1"},{"temp=":"$r"},"str",{"->":".^.s"},[{"#n":"$r1"}],"/str","/ev",{"*":".^.^.c-3","flg":18},{"s":["^\"To save hundreds of lives!\"",{"->":"$r","var":true},null]}],{"c-2":["ev",{"^->":"angry_old_man.1.c-1.5.g-0.c-2.$r2"},"/ev",{"temp=":"$r"},{"->":".^.^.2.s"},[{"#n":"$r2"}],"\n","^\"That's a shit reason.  Selfish.  Leave me alone.\"","\n","^The man goes back to his meal.","\n",{"->t->":"confirm"},{"->":"next","var":true},{"#f":5}],"c-3":["ev",{"^->":"angry_old_man.1.c-1.5.g-0.c-3.$r2"},"/ev",{"temp=":"$r"},{"->":".^.^.3.s"},[{"#n":"$r2"}],"\n","^\"Who says they need saving? What if it's just their time to die?\"","\n",[["ev",{"^->":"angry_old_man.1.c-1.5.g-0.c-3.9.0.$r1"},{"temp=":"$r"},"str",{"->":".^.s"},[{"#n":"$r1"}],"/str","/ev",{"*":".^.^.c-0","flg":18},{"s":["^\"What if it's not?\"",{"->":"$r","var":true},null]}],["ev",{"^->":"angry_old_man.1.c-1.5.g-0.c-3.9.1.$r1"},{"temp=":"$r"},"str",{"->":".^.s"},[{"#n":"$r1"}],"/str","/ev",{"*":".^.^.c-1","flg":18},{"s":["^\"Why would you say something like that?\"",{"->":"$r","var":true},null]}],{"c-0":["ev",{"^->":"angry_old_man.1.c-1.5.g-0.c-3.9.c-0.$r2"},"/ev",{"temp=":"$r"},{"->":".^.^.0.s"},[{"#n":"$r2"}],"\n",{"->":".^.^.g-0"},{"#f":5}],"c-1":["ev",{"^->":"angry_old_man.1.c-1.5.g-0.c-3.9.c-1.$r2"},"/ev",{"temp=":"$r"},{"->":".^.^.1.s"},[{"#n":"$r2"}],"\n",{"->":".^.^.g-0"},{"#f":5}],"g-0":["^The man grunts dismissively.  \"If it wasn't their time to die then God wouldn't have sent them diptheria.\"","\n","ev","str","^Fight him.","/str","/ev",{"*":".^.c-2","flg":20},"ev","str","^Leave him alone.","/str","/ev",{"*":".^.c-3","flg":20},{"c-2":["\n","ev",{"VAR?":"party"},"lrnd","/ev",{"temp=":"who"},"\n","ev",{"VAR?":"who"},{"x()":"name","exArgs":1},"out","/ev","^ puches the man in the face.  A fracas ensues.","\n","ev",1,100,"rnd",50,"<=","/ev",[{"->":".^.b","c":true},{"b":["\n","^He goes down quickly. You leave him unconscious in a corner.","\n","ev",true,"/ev",{"VAR=":"knocked_out_old_man","re":true},{"->t->":"confirm"},{"->":"next","var":true},{"->":".^.^.^.23"},null]}],[{"->":".^.b"},{"b":["\n","ev",{"VAR?":"who"},{"x()":"name","exArgs":1},"out","/ev","^ comes out of it with a broken nose. ",{"#":"bad"},"\n","ev",{"VAR?":"broken_nose"},{"VAR?":"who"},"+",{"VAR=":"broken_nose","re":true},"/ev","^\"That'll teach you to mess with God's plan!\" cackles the old bastard.","\n","^You decide not to pursue this any further.","\n",{"->t->":"confirm"},{"->":"next","var":true},{"->":".^.^.^.23"},null]}],"nop","\n",{"#f":5}],"c-3":["\n","^You decide not to pursue this any further.","\n",{"->t->":"confirm"},{"->":"next","var":true},"done",{"#f":5}]}]}],{"#f":5}]}]}],{"#f":5}]}],null],"gamblers":[{"temp=":"next"},["^You are not alone here.  ",["ev","visit",1,"MIN","/ev","ev","du",0,"==","/ev",{"->":".^.s0","c":true},"ev","du",1,"==","/ev",{"->":".^.s1","c":true},"nop",{"s0":["pop","^Some shady-looking folks are playing craps in the corner.",{"->":".^.^.17"},null],"s1":["pop","^The gamblers are still playing craps in the corner.",{"->":".^.^.17"},null],"#f":5}],"\n","ev","str","^Approach the gamblers.","/str",{"CNT?":".^.c-0.16.c-1"},"!","/ev",{"*":".^.c-0","flg":5},{"c-0":["\n","ev",{"VAR?":"party"},{"f()":"select_from"},"pop","/ev","\n","ev",{"VAR?":"WHO"},{"x()":"name","exArgs":1},"out","/ev","^ approaches the gamblers.  One of them looks up.","\n","^\"Wanna play?\" they ask.","\n",[["ev",{"^->":"gamblers.1.c-0.16.0.$r1"},{"temp=":"$r"},"str",{"->":".^.s"},[{"#n":"$r1"}],"/str","/ev",{"*":".^.^.c-0","flg":2},{"s":["^\"No\"",{"->":"$r","var":true},null]}],["ev",{"^->":"gamblers.1.c-0.16.1.$r1"},{"temp=":"$r"},"str",{"->":".^.s"},[{"#n":"$r1"}],"/str","/ev",{"*":".^.^.c-1","flg":2},{"s":["^\"Sure.\"",{"->":"$r","var":true},null]}],{"c-0":["ev",{"^->":"gamblers.1.c-0.16.c-0.$r2"},"/ev",{"temp=":"$r"},{"->":".^.^.0.s"},[{"#n":"$r2"}],"\n","^\"Then leave us alone\" one of the others pipes up.","\n",{"->t->":"confirm"},{"->":"next","var":true},null],"c-1":["ev",{"^->":"gamblers.1.c-0.16.c-1.$r2"},"/ev",{"temp=":"$r"},{"->":".^.^.1.s"},[{"#n":"$r2"}],"\n","ev",{"VAR?":"items"},"LIST_ALL",{"VAR?":"inventory"},"-","lrnd","/ev",{"temp=":"their_wager"},"\n","ev",{"VAR?":"inventory"},"lrnd","/ev",{"temp=":"your_wager"},"\n","ev",{"VAR?":"their_wager"},"!","/ev",[{"->":".^.b","c":true},{"b":["\n","^The gamblers get excited, until they realize that they have nothing of value that you don't already have.","\n",{"->t->":"confirm"},{"->":"next","var":true},{"->":".^.^.^.27"},null]}],"nop","\n","ev",{"VAR?":"your_wager"},"!","/ev",[{"->":".^.b","c":true},{"b":["\n","ev",{"VAR?":"WHO"},{"x()":"name","exArgs":1},"out","/ev","^ tries to join the gamblers, but it turns out that they're not interested in anything you have to wager.","\n",{"->t->":"confirm"},{"->":"next","var":true},{"->":".^.^.^.34"},null]}],"nop","\n","^\"How's this for a wager: my ","ev",{"VAR?":"their_wager"},"out","/ev","^ vs. your ","ev",{"VAR?":"your_wager"},"out","/ev","^?\"","\n",["ev","str","^Accept.","/str","/ev",{"*":".^.c-0","flg":20},"ev","str","^Decline.","/str","/ev",{"*":".^.c-1","flg":20},{"c-0":["\n","^You accept. ","ev",{"VAR?":"WHO"},{"x()":"name","exArgs":1},"out","/ev","^ rolls the dice.","\n","ev",1,100,"rnd",50,"<=","/ev",[{"->":".^.b","c":true},{"b":["\n","^It's a seven! You win!","\n","^The gamblers grumble as you take their ","ev",{"VAR?":"their_wager"},"out","/ev","^. ",{"#":"good"},"\n","ev",{"VAR?":"inventory"},{"VAR?":"their_wager"},"+",{"VAR=":"inventory","re":true},"/ev",{"->":".^.^.^.18"},null]}],[{"->":".^.b"},{"b":["\n","^Snake eyes! You lose!","\n","^The gamblers happily collect your ","ev",{"VAR?":"your_wager"},"out","/ev","^ from you. ",{"#":"bad"},"\n","ev",{"VAR?":"inventory"},{"VAR?":"your_wager"},"-",{"VAR=":"inventory","re":true},"/ev",{"->":".^.^.^.18"},null]}],"nop","\n",{"->t->":"confirm"},{"->":"next","var":true},{"#f":5}],"c-1":["\n","^You decline the wager.  The gamblers seem annoyed, and go back to ignoring you.","\n",{"->t->":"confirm"},{"->":"next","var":true},"done",{"#f":5}]}],{"#f":5}]}],null]}],null],"bear_attack":[{"temp=":"next_noskip"},{"temp=":"next_skip"},["^You approach the next roadhouse.  It looks dark. The door seems to be damaged, hanging off the hinges.","\n","ev","str","^Carry on to the next roadhouse.","/str","/ev",{"*":".^.c-0","flg":20},"ev","str","^Investigate.","/str","/ev",{"*":".^.c-1","flg":20},{"c-0":["\n","^You decide to carry on to the next roadhouse.","\n",{"->t->":"confirm"},{"->":"next_skip","var":true},{"->":".^.^.g-0"},{"#f":5}],"c-1":["\n",{"->":".^.^.g-0"},{"#f":5}],"g-0":["^There seems to be blood on the walls of the roadhouse.","\n","^Outside the building, two roughly human-sized objects are buried under freshly-fallen snow.","\n",["ev","str","^Dig under the snow.","/str","/ev",{"*":".^.c-2","flg":20},"ev","str","^Shine a light inside.","/str",{"VAR?":"inventory"},{"VAR?":"lamp"},"?","/ev",{"*":".^.c-3","flg":21},"ev","str","^Leave immediately.","/str","/ev",{"*":".^.c-4","flg":20},"ev","str","^Enter the building.","/str","/ev",{"*":".^.c-5","flg":20},{"c-2":["\n","^You uncover two bloody corpses.","\n","ev",{"f()":"dead_body_seen"},"pop","/ev","\n",{"->":".^.^"},{"->":".^.^.^.^.g-1"},{"#f":5}],"c-3":["\n","^You shine your lamp through the door and see a large polar bear, its jaws covered in blood, sleeping in a corner.","\n",{"->":".^.^"},{"->":".^.^.^.^.g-1"},{"#f":5}],"c-4":["\n","^You decide to get the hell outta there.","\n",{"->t->":"confirm"},{"->":"next_skip","var":true},{"->":".^.^.^.^.g-1"},{"#f":5}],"c-5":["\n",{"->":".^.^.^.^.g-1"},{"#f":5}],"#n":"options"}],null],"g-1":["ev",{"VAR?":"party"},{"f()":"select_from"},"pop","/ev","\n","ev",{"VAR?":"WHO"},{"x()":"name","exArgs":1},"out","/ev","^ enters the building, waking the giant polar bear sleeping in a corner.  It rises up to a truly staggering height, growling and baring its sharp teeth.","\n","ev","str","^Leave ","ev",{"VAR?":"WHO"},{"x()":"name","exArgs":1},"out","/ev","^ and run.","/str",{"VAR?":"party"},"LIST_COUNT",1,">","/ev",{"*":".^.c-6","flg":21},"ev","str","^Fight.","/str","/ev",{"*":".^.c-7","flg":20},{"c-6":["\n","^The rest of the party runs, leaving ","ev",{"VAR?":"WHO"},{"x()":"name","exArgs":1},"out","/ev","^ to die. ",{"#":"bad"},{"#":"severe"},"\n","ev",{"VAR?":"WHO"},{"f()":"kill"},"pop","/ev","\n",{"->t->":"confirm"},{"->t->":"next_skip","var":true},{"->":".^.^.^.g-2"},{"#f":5}],"c-7":["\n","ev",{"VAR?":"inventory"},{"VAR?":"shotgun"},"?","/ev",[{"->":".^.b","c":true},{"b":["\n","^You grab the shotgun and shoot the bear several times.","\n","^It puts up a brave fight, but you eventually kill it and escape mostly unharmed.","\n","ev",{"VAR?":"party"},{"VAR?":"bruised"},"-",{"f()":"select_from"},"/ev",[{"->":".^.b","c":true},{"b":["\n","ev",{"VAR?":"bruised"},{"VAR?":"WHO"},"+",{"VAR=":"bruised","re":true},"/ev","ev",{"VAR?":"WHO"},{"x()":"name","exArgs":1},"out","/ev","^ obtains some minor injuries. ",{"#":"bad"},"\n",{"->":".^.^.^.12"},null]}],"nop","\n",{"->":".^.^.^.8"},null]}],[{"->":".^.b"},{"b":["\n","^You attempt to engage in unarmed combat with a polar bear.","\n","ev",{"VAR?":"party"},{"f()":"select_from"},"pop","/ev","\n","^Amazingly, you kill the bear.","\n","^But ","ev",{"VAR?":"WHO"},{"x()":"name","exArgs":1},"out","/ev","^ dies in the process. ",{"#":"bad"},{"#":"severe"},"\n",{"->":".^.^.^.8"},null]}],"nop","\n",{"->":".^.^.^.g-2"},{"#f":5}]}],"g-2":[{"->t->":"confirm"},{"->":"next_noskip","var":true},null]}],{"#f":1}],"random_event":[["ev",1,100,"rnd",50,"<=","/ev",[{"->":".^.b","c":true},{"b":["\n","ev","void","/ev","->->",{"->":".^.^.^.8"},null]}],"nop","\n","ev",1,11,"rnd","/ev",["du","ev",1,"==","/ev",{"->":".^.b","c":true},{"b":["pop","\n",{"->t->":"sled_bump"},{"->":".^.^.^.27"},null]}],["du","ev",2,"==","/ev",{"->":".^.b","c":true},{"b":["pop","\n",{"->t->":"wolf_pack"},{"->":".^.^.^.27"},null]}],["du","ev",3,"==","/ev",{"->":".^.b","c":true},{"b":["pop","\n",{"->t->":"blizzard_start"},{"->":".^.^.^.27"},null]}],["du","ev",4,"==","/ev",{"->":".^.b","c":true},{"b":["pop","\n",{"->t->":"aurora_good_start"},{"->":".^.^.^.27"},null]}],["du","ev",5,"==","/ev",{"->":".^.b","c":true},{"b":["pop","\n",{"->t->":"aurora_bad_start"},{"->":".^.^.^.27"},null]}],["du","ev",6,"==","/ev",{"->":".^.b","c":true},{"b":["pop","\n",{"->t->":"hail_start"},{"->":".^.^.^.27"},null]}],["du","ev",7,"==","/ev",{"->":".^.b","c":true},{"b":["pop","\n",{"->t->":"cairn"},{"->":".^.^.^.27"},null]}],["du","ev",8,"==","/ev",{"->":".^.b","c":true},{"b":["pop","\n",{"->t->":"sled_obstacle"},{"->":".^.^.^.27"},null]}],["du","ev",9,"==","/ev",{"->":".^.b","c":true},{"b":["pop","\n",{"->t->":"unsettling_experience"},{"->":".^.^.^.27"},null]}],["du","ev",10,"==","/ev",{"->":".^.b","c":true},{"b":["pop","\n",{"->t->":"argument"},{"->":".^.^.^.27"},null]}],["du","ev",11,"==","/ev",{"->":".^.b","c":true},{"b":["pop","\n",{"->t->":"get_dysentery"},{"->":".^.^.^.27"},null]}],"pop","nop","\n","ev","str","^Ok","/str","/ev",{"*":".^.c-0","flg":4},{"c-0":["\n",{"->":".^.^.g-0"},null],"g-0":["ev","void","/ev","->->",null]}],null],"get_dysentery":["ev",{"VAR?":"party"},{"VAR?":"dysentery"},"-",{"f()":"select_from"},"/ev",[{"->":".^.b","c":true},{"b":["\n","ev",{"VAR?":"dysentery"},{"VAR?":"WHO"},"+",{"VAR=":"dysentery","re":true},"/ev","ev",{"VAR?":"WHO"},{"x()":"name","exArgs":1},"out","/ev","^ seems to have contracted dysentery. ",{"#":"bad"},"\n",{"->":".^.^.^.8"},null]}],[{"->":".^.b"},{"b":["\n","^Everyone in your party continues to have dysentery.","\n",{"->":".^.^.^.8"},null]}],"nop","\n","ev","void","/ev","->->",null],"unsettling_experience":[["ev","visit",4,"seq","/ev","ev","du",0,"==","/ev",{"->":".^.s0","c":true},"ev","du",1,"==","/ev",{"->":".^.s1","c":true},"ev","du",2,"==","/ev",{"->":".^.s2","c":true},"ev","du",3,"==","/ev",{"->":".^.s3","c":true},"nop",{"s0":["pop","^The sky almost seems... too far away?",{"->":".^.^.29"},null],"s1":["pop","^The wind shouldn't sound like that, should it?",{"->":".^.^.29"},null],"s2":["pop","^It ain't being dead - it's the awful dread of the icy grave that pains...",{"->":".^.^.29"},null],"s3":["pop","^You get the feeling that there's something unnatural out there in the darkness.",{"->":".^.^.29"},null],"#f":5}],"\n","ev",{"VAR?":"party"},{"VAR?":"stressed"},"-",{"f()":"select_from"},"/ev",[{"->":".^.b","c":true},{"b":["\n","ev",{"VAR?":"stressed"},{"VAR?":"WHO"},"+",{"VAR=":"stressed","re":true},"/ev","ev",{"VAR?":"WHO"},{"x()":"name","exArgs":1},"out","/ev","^ is not feeling great. ",{"#":"bad"},"\n",{"->":".^.^.^.9"},null]}],"nop","\n","ev","void","/ev","->->",null],"argument":[["ev",{"VAR?":"party"},"LIST_COUNT",2,"<","/ev",[{"->":".^.b","c":true},{"b":["\n","ev",{"VAR?":"party"},{"f()":"select_from"},"pop","/ev","\n","ev",{"VAR?":"agitated"},{"VAR?":"WHO"},"+",{"VAR=":"agitated","re":true},"/ev","ev",{"VAR?":"WHO"},{"x()":"name","exArgs":1},"out","/ev","^ has started mumbling angrily to themselves. ",{"#":"bad"},"\n","ev","void","/ev","->->",{"->":".^.^.^.7"},null]}],"nop","\n","ev",{"VAR?":"party"},"lrnd","/ev",{"temp=":"person1"},"\n","ev",{"VAR?":"party"},{"VAR?":"person1"},"-","lrnd","/ev",{"temp=":"person2"},"\n","ev",{"VAR?":"person1"},"/ev",{"temp=":"loser"},"ev",{"VAR?":"person1"},{"x()":"name","exArgs":1},"out","/ev","^ and ","ev",{"VAR?":"person2"},{"x()":"name","exArgs":1},"out","/ev","^ are having a heated argument.","\n","ev",{"VAR?":"person1"},{"x()":"name","exArgs":1},"out","/ev","^ ",["ev","visit",3,"seq","/ev","ev","du",0,"==","/ev",{"->":".^.s0","c":true},"ev","du",1,"==","/ev",{"->":".^.s1","c":true},"ev","du",2,"==","/ev",{"->":".^.s2","c":true},"nop",{"s0":["pop","^believes",{"->":".^.^.23"},null],"s1":["pop","^claims",{"->":".^.^.23"},null],"s2":["pop","^says",{"->":".^.^.23"},null],"#f":5}],"^ that ",["ev","visit",10,"seq","/ev","ev","du",0,"==","/ev",{"->":".^.s0","c":true},"ev","du",1,"==","/ev",{"->":".^.s1","c":true},"ev","du",2,"==","/ev",{"->":".^.s2","c":true},"ev","du",3,"==","/ev",{"->":".^.s3","c":true},"ev","du",4,"==","/ev",{"->":".^.s4","c":true},"ev","du",5,"==","/ev",{"->":".^.s5","c":true},"ev","du",6,"==","/ev",{"->":".^.s6","c":true},"ev","du",7,"==","/ev",{"->":".^.s7","c":true},"ev","du",8,"==","/ev",{"->":".^.s8","c":true},"ev","du",9,"==","/ev",{"->":".^.s9","c":true},"nop",{"s0":["pop","^mankind is alone in the universe",{"->":".^.^.65"},null],"s1":["pop","^there is no god",{"->":".^.^.65"},null],"s2":["pop","^objective truth is unattainable",{"->":".^.^.65"},null],"s3":["pop","^a communist revolution is inevitable",{"->":".^.^.65"},null],"s4":["pop","^true altruism does not exist, and all seemingly 'selfless' acts are in fact selfishly motivated",{"->":".^.^.65"},null],"s5":["pop","^happiness is unobtainable",{"->":".^.^.65"},null],"s6":["pop","^there is some sense in which we die every time we go to sleep",{"->":".^.^.65"},null],"s7":["pop","^the industrial revolution has done more harm than good",{"->":".^.^.65"},null],"s8":["pop","^pineapple goes well on pizza",{"->":".^.^.65"},null],"s9":["pop","^air travel will never be commercially viable",{"->":".^.^.65"},null],"#f":5}],"^.  ","ev",{"VAR?":"person2"},{"x()":"name","exArgs":1},"out","/ev","^ disagrees.","\n","ev","str","^Resolve in favour of ","ev",{"VAR?":"person1"},{"x()":"name","exArgs":1},"out","/ev","^.","/str","/ev",{"*":".^.c-0","flg":4},"ev","str","^Resolve in favour of ","ev",{"VAR?":"person2"},{"x()":"name","exArgs":1},"out","/ev","^.","/str","/ev",{"*":".^.c-1","flg":4},{"c-0":["\n","ev",{"VAR?":"person2"},"/ev",{"temp=":"loser","re":true},{"->":".^.^.g-0"},null],"c-1":["\n","ev",{"VAR?":"person1"},"/ev",{"temp=":"loser","re":true},{"->":".^.^.g-0"},null],"g-0":["ev",{"VAR?":"agitated"},{"VAR?":"loser"},"+",{"VAR=":"agitated","re":true},"/ev","ev",{"VAR?":"loser"},{"x()":"name","exArgs":1},"out","/ev","^ didn't like that. ",{"#":"bad"},"\n","ev","void","/ev","->->",null]}],null],"sled_bump":["^You hit a bump in the trail.","\n","ev",{"VAR?":"party"},{"VAR?":"bruised"},"-",{"f()":"select_from"},"/ev",[{"->":".^.b","c":true},{"b":["\n","ev",{"VAR?":"bruised"},{"VAR?":"WHO"},"+",{"VAR=":"bruised","re":true},"/ev","ev",{"VAR?":"WHO"},{"x()":"name","exArgs":1},"out","/ev","^ gets roughed up a bit. ",{"#":"bad"},"\n",{"->":".^.^.^.9"},null]}],"nop","\n","ev","void","/ev","->->",null],"sled_obstacle":["^A log half-covered by the deep snow emerges out of the darkness ahead.","\n","ev",{"VAR?":"inventory"},{"VAR?":"lamp"},"?","/ev",[{"->":".^.b","c":true},{"b":["\n","^Fortunately, the light of your lamp gives you adequate warning to avoid hitting it.","\n",{"->":".^.^.^.9"},null]}],[{"->":".^.b"},{"b":["\n","^By the time you see it there's no time to turn or stop the sled.","\n","ev",{"VAR?":"party"},{"VAR?":"broken_leg"},"-",{"f()":"select_from"},"/ev",[{"->":".^.b","c":true},{"b":["\n","ev",{"VAR?":"broken_leg"},{"VAR?":"WHO"},"+",{"VAR=":"broken_leg","re":true},"/ev","ev",{"VAR?":"WHO"},{"x()":"name","exArgs":1},"out","/ev","^ breaks a leg in the ensuing collision. ",{"#":"bad"},"\n",{"->":".^.^.^.10"},null]}],"nop","\n",{"->":".^.^.^.9"},null]}],"nop","\n","ev","void","/ev","->->",null],"wolf_pack":[["^A pack of wolves emerge from the night behind you, ",["ev","visit",5,"seq","/ev","ev","du",0,"==","/ev",{"->":".^.s0","c":true},"ev","du",1,"==","/ev",{"->":".^.s1","c":true},"ev","du",2,"==","/ev",{"->":".^.s2","c":true},"ev","du",3,"==","/ev",{"->":".^.s3","c":true},"ev","du",4,"==","/ev",{"->":".^.s4","c":true},"nop",{"s0":["pop","^ long teeth glinting in the starlight",{"->":".^.^.35"},null],"s1":["pop","^bearing down on you with a surprising sense of purpose and coordination",{"->":".^.^.35"},null],"s2":["pop","^moving in unison with terrifying speed and precision",{"->":".^.^.35"},null],"s3":["pop","^chasing after you with ravenous expressions and glowing eyes",{"->":".^.^.35"},null],"s4":["pop","^led by a particularly ferocious animal covered in scars",{"->":".^.^.35"},null],"#f":5}],"^.  They're coming quickly, but your dogs are faster (hopefully).","\n","ev","str","^Outrun them","/str","/ev",{"*":".^.c-0","flg":4},"ev","str","^Throw something at them","/str",{"VAR?":"inventory"},"LIST_COUNT",0,">","/ev",{"*":".^.c-1","flg":5},"ev","str","^Shoot at them","/str",{"VAR?":"inventory"},{"VAR?":"shotgun"},"?","/ev",{"*":".^.c-2","flg":5},{"c-0":["\n","^You urge the dogs to run faster.  They don't need any convincing.","\n","^Eventually the wolves give up and you escape with your life.","\n","ev",{"VAR?":"party"},{"VAR?":"terrified"},"-",{"f()":"select_from"},"/ev",[{"->":".^.b","c":true},{"b":["\n","ev",{"VAR?":"terrified"},{"VAR?":"WHO"},"+",{"VAR=":"terrified","re":true},"/ev","ev",{"VAR?":"WHO"},{"x()":"name","exArgs":1},"out","/ev","^ seems shaken by the encounter. ",{"#":"bad"},"\n",{"->":".^.^.^.12"},null]}],"nop","\n",{"->":".^.^.g-0"},null],"c-1":["\n","ev",{"VAR?":"inventory"},"lrnd","/ev",{"temp=":"to_throw"},"\n","ev",{"VAR?":"inventory"},{"VAR?":"to_throw"},"-",{"VAR=":"inventory","re":true},"/ev","^Terrified, you throw your ","ev",{"VAR?":"to_throw"},"out","/ev","^ at the wolves.  They appear to back off, but going back to retrieve the ","ev",{"VAR?":"to_throw"},"out","/ev","^ is definitely off the table.","\n",{"->":".^.^.g-0"},null],"c-2":["\n","^You grab the shotgun and fire at the pack.  They back off.","\n",{"->":".^.^.g-0"},null],"g-0":["ev","void","/ev","->->",null]}],null],"cairn":[["^You spot a long-forgotten, lonely cairn of stones.","\n","ev","str","^Leave it.","/str","/ev",{"*":".^.c-0","flg":4},"ev","str","^Investigate.","/str","/ev",{"*":".^.c-1","flg":4},{"c-0":["\n","^You leave the cairn alone.","\n",{"->":".^.^.g-0"},null],"c-1":["\n","ev",false,"/ev",{"VAR=":"currently_moving","re":true},"^Buried beneath the cairn you find only weathered, broken bones.","\n","ev",{"f()":"dead_body_seen"},"pop","/ev","\n",{"->":".^.^.g-0"},null],"g-0":["ev","void","/ev","->->",null]}],null],"blizzard_start":["^A blizzard starts.","\n","ev",{"VAR?":"blizzard"},"/ev",{"VAR=":"weather","re":true},"ev","void","/ev","->->",null],"aurora_good_start":["^The sky ",["ev","visit",2,"seq","/ev","ev","du",0,"==","/ev",{"->":".^.s0","c":true},"ev","du",1,"==","/ev",{"->":".^.s1","c":true},"nop",{"s0":["pop","^lights up",{"->":".^.^.17"},null],"s1":["pop","^comes alive",{"->":".^.^.17"},null],"#f":5}],"^ in a ",["ev","visit",3,"seq","/ev","ev","du",0,"==","/ev",{"->":".^.s0","c":true},"ev","du",1,"==","/ev",{"->":".^.s1","c":true},"ev","du",2,"==","/ev",{"->":".^.s2","c":true},"nop",{"s0":["pop","^stunning",{"->":".^.^.23"},null],"s1":["pop","^dazzling",{"->":".^.^.23"},null],"s2":["pop","^awe-inspiring",{"->":".^.^.23"},null],"#f":5}],"^ array of colours.","\n","ev",{"VAR?":"aurora_good"},"/ev",{"VAR=":"weather","re":true},"ev","void","/ev","->->",null],"aurora_bad_start":["^The sky ",["ev","visit",2,"seq","/ev","ev","du",0,"==","/ev",{"->":".^.s0","c":true},"ev","du",1,"==","/ev",{"->":".^.s1","c":true},"nop",{"s0":["pop","^erupts",{"->":".^.^.17"},null],"s1":["pop","^is set aflame",{"->":".^.^.17"},null],"#f":5}],"^ in ",["ev","visit",3,"seq","/ev","ev","du",0,"==","/ev",{"->":".^.s0","c":true},"ev","du",1,"==","/ev",{"->":".^.s1","c":true},"ev","du",2,"==","/ev",{"->":".^.s2","c":true},"nop",{"s0":["pop","^a terrifying",{"->":".^.^.23"},null],"s1":["pop","^an ominous",{"->":".^.^.23"},null],"s2":["pop","^a deeply menacing",{"->":".^.^.23"},null],"#f":5}],"^ shade of red.","\n","ev",{"VAR?":"aurora_bad"},"/ev",{"VAR=":"weather","re":true},"ev","void","/ev","->->",null],"hail_start":["^A hailstorm starts.","\n","ev",{"VAR?":"hail"},"/ev",{"VAR=":"weather","re":true},"ev","void","/ev","->->",null],"describe_weather":["ev",{"VAR?":"weather"},"/ev",["du","ev",{"VAR?":"normal"},"==","/ev",{"->":".^.b","c":true},{"b":["pop","\n","^The sky is clear.","\n",{"->":".^.^.^.9"},null]}],["du","ev",{"VAR?":"blizzard"},"==","/ev",{"->":".^.b","c":true},{"b":["pop","\n","^A blizzard rages around you.","\n",{"->":".^.^.^.9"},null]}],["du","ev",{"VAR?":"aurora_good"},"==","/ev",{"->":".^.b","c":true},{"b":["pop","\n","^In the clear sky, ",["ev","visit",4,"seq","/ev","ev","du",0,"==","/ev",{"->":".^.s0","c":true},"ev","du",1,"==","/ev",{"->":".^.s1","c":true},"ev","du",2,"==","/ev",{"->":".^.s2","c":true},"ev","du",3,"==","/ev",{"->":".^.s3","c":true},"nop",{"s0":["pop","^beautiful",{"->":".^.^.29"},null],"s1":["pop","^awe-inspiring",{"->":".^.^.29"},null],"s2":["pop","^calming",{"->":".^.^.29"},null],"s3":["pop","^gentle",{"->":".^.^.29"},null],"#f":5}],"^ aurorae ",["ev","visit",5,"seq","/ev","ev","du",0,"==","/ev",{"->":".^.s0","c":true},"ev","du",1,"==","/ev",{"->":".^.s1","c":true},"ev","du",2,"==","/ev",{"->":".^.s2","c":true},"ev","du",3,"==","/ev",{"->":".^.s3","c":true},"ev","du",4,"==","/ev",{"->":".^.s4","c":true},"nop",{"s0":["pop","^shimmer and dance",{"->":".^.^.35"},null],"s1":["pop","^undulate",{"->":".^.^.35"},null],"s2":["pop","^smile down upon you",{"->":".^.^.35"},null],"s3":["pop","^accompany you",{"->":".^.^.35"},null],"s4":["pop","^inspire you",{"->":".^.^.35"},null],"#f":5}],"^.","\n",{"->":".^.^.^.9"},null]}],["du","ev",{"VAR?":"aurora_bad"},"==","/ev",{"->":".^.b","c":true},{"b":["pop","\n","^In the clear sky, ",["ev","visit",4,"seq","/ev","ev","du",0,"==","/ev",{"->":".^.s0","c":true},"ev","du",1,"==","/ev",{"->":".^.s1","c":true},"ev","du",2,"==","/ev",{"->":".^.s2","c":true},"ev","du",3,"==","/ev",{"->":".^.s3","c":true},"nop",{"s0":["pop","^terrifying",{"->":".^.^.29"},null],"s1":["pop","^ominous",{"->":".^.^.29"},null],"s2":["pop","^deeply menacing",{"->":".^.^.29"},null],"s3":["pop","^terrible",{"->":".^.^.29"},null],"#f":5}],"^ aurorae ",["ev","visit",4,"seq","/ev","ev","du",0,"==","/ev",{"->":".^.s0","c":true},"ev","du",1,"==","/ev",{"->":".^.s1","c":true},"ev","du",2,"==","/ev",{"->":".^.s2","c":true},"ev","du",3,"==","/ev",{"->":".^.s3","c":true},"nop",{"s0":["pop","^burn angrily",{"->":".^.^.29"},null],"s1":["pop","^flicker strangely",{"->":".^.^.29"},null],"s2":["pop","^obscure the lonely stars",{"->":".^.^.29"},null],"s3":["pop","^glare down upon you",{"->":".^.^.29"},null],"#f":5}],"^.","\n",{"->":".^.^.^.9"},null]}],["du","ev",{"VAR?":"hail"},"==","/ev",{"->":".^.b","c":true},{"b":["pop","\n","^Hailstones the size of ",["ev","visit",3,"seq","/ev","ev","du",0,"==","/ev",{"->":".^.s0","c":true},"ev","du",1,"==","/ev",{"->":".^.s1","c":true},"ev","du",2,"==","/ev",{"->":".^.s2","c":true},"nop",{"s0":["pop","^eggs",{"->":".^.^.23"},null],"s1":["pop","^fists",{"->":".^.^.23"},null],"s2":["pop","^very large hailstones",{"->":".^.^.23"},null],"#f":5}],"^ are falling all around you.","\n",{"->":".^.^.^.9"},null]}],"pop","nop","\n","ev","void","/ev","->->",null],"process_weather":["ev",{"VAR?":"weather"},"/ev",["du","ev",{"VAR?":"normal"},"==","/ev",{"->":".^.b","c":true},{"b":["pop","\n",{"->":".^.^.^.9"},null]}],["du","ev",{"VAR?":"blizzard"},"==","/ev",{"->":".^.b","c":true},{"b":["pop","\n","ev",{"VAR?":"party"},{"^->":"cold_sim"},{"f()":"for_each"},"pop","/ev","\n",{"->":".^.^.^.9"},null]}],["du","ev",{"VAR?":"aurora_good"},"==","/ev",{"->":".^.b","c":true},{"b":["pop","\n","ev",{"VAR?":"party"},{"^->":"cheer_up"},{"f()":"for_each"},"pop","/ev","\n",{"->":".^.^.^.9"},null]}],["du","ev",{"VAR?":"aurora_bad"},"==","/ev",{"->":".^.b","c":true},{"b":["pop","\n","ev",{"VAR?":"party"},{"^var":"stressed","ci":-1},"str","^stressed","/str",25,{"f()":"maybe_effect"},"pop","/ev","\n",{"->":".^.^.^.9"},null]}],["du","ev",{"VAR?":"hail"},"==","/ev",{"->":".^.b","c":true},{"b":["pop","\n","ev",{"VAR?":"party"},{"^var":"bruised","ci":-1},"str","^bruised","/str",5,{"f()":"maybe_effect"},"pop","/ev","\n",{"->":".^.^.^.9"},null]}],"pop","nop","\n","ev",1,100,"rnd",15,"<=","/ev",[{"->":".^.b","c":true},{"b":["\n","ev",{"VAR?":"normal"},"/ev",{"VAR=":"weather","re":true},{"->":".^.^.^.19"},null]}],"nop","\n","ev","void","/ev","->->",null],"global decl":["ev",{"list":{},"origins":["notification_types"]},{"VAR=":"notification_types"},72,{"VAR=":"hours_remaining"},100,{"VAR=":"serum"},4,{"VAR=":"dogs_remaining"},2,{"VAR=":"morphine"},2,{"VAR=":"whiskey"},2,{"VAR=":"coffee"},0,{"VAR=":"sourdough"},0,{"VAR=":"jerky"},{"list":{},"origins":["items"]},{"VAR=":"items"},{"list":{}},{"VAR=":"inventory"},{"list":{"party.p1":1,"party.p2":2,"party.p3":3,"party.p4":4}},{"VAR=":"party"},{"list":{}},{"VAR=":"dead"},{"list":{}},{"VAR=":"terrified"},{"list":{}},{"VAR=":"stressed"},{"list":{}},{"VAR=":"traumatized"},{"list":{}},{"VAR=":"agitated"},{"list":{}},{"VAR=":"guilty"},{"list":{}},{"VAR=":"broken_nose"},{"list":{}},{"VAR=":"broken_leg"},{"list":{}},{"VAR=":"bruised"},{"list":{}},{"VAR=":"dysentery"},{"list":{}},{"VAR=":"in_pain"},{"list":{}},{"VAR=":"hungry"},{"list":{}},{"VAR=":"starving"},{"list":{}},{"VAR=":"cold"},{"list":{}},{"VAR=":"hypothermic"},{"list":{}},{"VAR=":"tired"},{"list":{}},{"VAR=":"exhausted"},true,{"VAR=":"ate"},true,{"VAR=":"rested"},true,{"VAR=":"slept"},true,{"VAR=":"played_music"},false,{"VAR=":"fire_lit"},false,{"VAR=":"has_bed"},false,{"VAR=":"has_piano"},false,{"VAR=":"has_old_man"},{"list":{},"origins":["landmarks"]},{"VAR=":"landmarks"},{"VAR?":"start_location"},{"VAR=":"current_location"},false,{"VAR=":"knocked_out_old_man"},{"list":{"weather.normal":1}},{"VAR=":"weather"},{"list":{}},{"VAR=":"WHO"},false,{"VAR=":"currently_moving"},"/ev","end",null]}],"listDefs":{"notification_types":{"good":1,"bad":2},"items":{"lamp":1,"shotgun":2,"harmonica":3,"saucepan":4,"bedroll":5,"bible":6},"party":{"p1":1,"p2":2,"p3":3,"p4":4},"landmarks":{"start_location":1,"rh1":2,"rh2":3,"old_man_roadhouse":4,"gambling_roadhouse":5,"rh3":6,"missing_roadhouse":7,"bear_roadhouse":8,"rh4":9,"last_roadhouse":10,"final_destination":11,"debug_location":12},"weather":{"normal":1,"blizzard":2,"aurora_good":3,"aurora_bad":4,"hail":5}}}